Workbook

Sheet Canada summary
A1: Canada: immediate expensing for machinery and buildings - weighted-average NPV and OECD rank, 2026-2030
A2: Values link to the per-year sheets. Rank change is positive when the reform improves Canada rank (current-law rank minus reform rank).
A4: Year | B4: Weighted avg (current law) | C4: Rank (current law) | D4: Weighted avg (reform) | E4: Rank (reform) | F4: Rank change (+ = better) | G4: Weighted-avg change
A5: =2026 -> 2026 | B5: ='2026'!F9 -> 0.85 | C5: ='2026'!G9 -> 5 | D5: ='2026'!K9 -> 1 | E5: ='2026'!L9 -> 1 | F5: =C5-E5 -> 4 | G5: =D5-B5 -> 0.15
A6: =2027 -> 2027 | B6: ='2027'!F9 -> 0.765 | C6: ='2027'!G9 -> 5 | D6: ='2027'!K9 -> 0.9149 | E6: ='2027'!L9 -> 5 | F6: =C6-E6 -> 0 | G6: =D6-B6 -> 0.1499
A7: =2028 -> 2028 | B7: ='2028'!F9 -> 0.765 | C7: ='2028'!G9 -> 5 | D7: ='2028'!K9 -> 0.9149 | E7: ='2028'!L9 -> 5 | F7: =C7-E7 -> 0 | G7: =D7-B7 -> 0.1499
A8: =2029 -> 2029 | B8: ='2029'!F9 -> 0.765 | C8: ='2029'!G9 -> 4 | D8: ='2029'!K9 -> 0.9149 | E8: ='2029'!L9 -> 4 | F8: =C8-E8 -> 0 | G8: =D8-B8 -> 0.1499
A9: =2030 -> 2030 | B9: ='2030'!F9 -> 0.7462 | C9: ='2030'!G9 -> 7 | D9: ='2030'!K9 -> 0.9149 | E9: ='2030'!L9 -> 4 | F9: =C9-E9 -> 3 | G9: =D9-B9 -> 0.1687

Sheet 2026
A1: Net Present Value of Capital Allowances, OECD Ranking 2026: current law vs. Canada immediate-expensing reform
A2: Weighted avg = weights (Notes) applied to asset NPVs (source: final-data/npv_all_years.csv). Reform sets Canada machinery and buildings to 1.0; intangibles unchanged. Ranks: RANK on weighted avg rounded to 4 dp, ties=min.
A4: Country | B4: ISO | C4: Buildings (current law) | D4: Machinery (current law) | E4: Intangibles (current law) | F4: Weighted avg (current law) | G4: Rank (current law) | H4: Buildings (reform) | I4: Machinery (reform) | J4: Intangibles (reform) | K4: Weighted avg (reform) | L4: Rank (reform)
A5: Estonia | B5: EST | C5: =1 -> 1 | D5: =1 -> 1 | E5: =1 -> 1 | F5: =ROUND(Notes!$B$4*D5+Notes!$B$5*C5+Notes!$B$6*E5,4) -> 1 | G5: =RANK(F5,F$5:F$42,0) -> 1 | H5: =C5 -> 1 | I5: =D5 -> 1 | J5: =E5 -> 1 | K5: =ROUND(Notes!$B$4*I5+Notes!$B$5*H5+Notes!$B$6*J5,4) -> 1 | L5: =RANK(K5,K$5:K$42,0) -> 1
A6: Latvia | B6: LVA | C6: =1 -> 1 | D6: =1 -> 1 | E6: =1 -> 1 | F6: =ROUND(Notes!$B$4*D6+Notes!$B$5*C6+Notes!$B$6*E6,4) -> 1 | G6: =RANK(F6,F$5:F$42,0) -> 1 | H6: =C6 -> 1 | I6: =D6 -> 1 | J6: =E6 -> 1 | K6: =ROUND(Notes!$B$4*I6+Notes!$B$5*H6+Notes!$B$6*J6,4) -> 1 | L6: =RANK(K6,K$5:K$42,0) -> 1
A7: United States | B7: USA | C7: =1 -> 1 | D7: =1 -> 1 | E7: =0.632751338890881 -> 0.63275134 | F7: =ROUND(Notes!$B$4*D7+Notes!$B$5*C7+Notes!$B$6*E7,4) -> 0.9452 | G7: =RANK(F7,F$5:F$42,0) -> 3 | H7: =C7 -> 1 | I7: =D7 -> 1 | J7: =E7 -> 0.63275134 | K7: =ROUND(Notes!$B$4*I7+Notes!$B$5*H7+Notes!$B$6*J7,4) -> 0.9452 | L7: =RANK(K7,K$5:K$42,0) -> 4
A8: Lithuania | B8: LTU | C8: =0.826923076923077 -> 0.82692308 | D8: =1 -> 1 | E8: =1 -> 1 | F8: =ROUND(Notes!$B$4*D8+Notes!$B$5*C8+Notes!$B$6*E8,4) -> 0.9288 | G8: =RANK(F8,F$5:F$42,0) -> 4 | H8: =C8 -> 0.82692308 | I8: =D8 -> 1 | J8: =E8 -> 1 | K8: =ROUND(Notes!$B$4*I8+Notes!$B$5*H8+Notes!$B$6*J8,4) -> 0.9288 | L8: =RANK(K8,K$5:K$42,0) -> 5
A9: Canada | B9: CAN | C9: =0.635714285714286 -> 0.63571429 | D9: =1 -> 1 | E9: =1 -> 1 | F9: =ROUND(Notes!$B$4*D9+Notes!$B$5*C9+Notes!$B$6*E9,4) -> 0.85 | G9: =RANK(F9,F$5:F$42,0) -> 5 | H9: =1 -> 1 | I9: =1 -> 1 | J9: =E9 -> 1 | K9: =ROUND(Notes!$B$4*I9+Notes!$B$5*H9+Notes!$B$6*J9,4) -> 1 | L9: =RANK(K9,K$5:K$42,0) -> 1
A10: Italy | B10: ITA | C10: =0.576669379707147 -> 0.57666938 | D10: =0.869865253929667 -> 0.86986525 | E10: =0.965116279069767 -> 0.96511628 | F10: =ROUND(Notes!$B$4*D10+Notes!$B$5*C10+Notes!$B$6*E10,4) -> 0.7634 | G10: =RANK(F10,F$5:F$42,0) -> 6 | H10: =C10 -> 0.57666938 | I10: =D10 -> 0.86986525 | J10: =E10 -> 0.96511628 | K10: =ROUND(Notes!$B$4*I10+Notes!$B$5*H10+Notes!$B$6*J10,4) -> 0.7634 | L10: =RANK(K10,K$5:K$42,0) -> 6
A11: Korea | B11: KOR | C11: =0.547953910556565 -> 0.54795391 | D11: =0.921720532319392 -> 0.92172053 | E11: =0.813463195231154 -> 0.8134632 | F11: =ROUND(Notes!$B$4*D11+Notes!$B$5*C11+Notes!$B$6*E11,4) -> 0.7517 | G11: =RANK(F11,F$5:F$42,0) -> 7 | H11: =C11 -> 0.54795391 | I11: =D11 -> 0.92172053 | J11: =E11 -> 0.8134632 | K11: =ROUND(Notes!$B$4*I11+Notes!$B$5*H11+Notes!$B$6*J11,4) -> 0.7517 | L11: =RANK(K11,K$5:K$42,0) -> 7
A12: Iceland | B12: ISL | C12: =0.602353618717047 -> 0.60235362 | D12: =0.86 -> 0.86 | E12: =0.812269350072009 -> 0.81226935 | F12: =ROUND(Notes!$B$4*D12+Notes!$B$5*C12+Notes!$B$6*E12,4) -> 0.7468 | G12: =RANK(F12,F$5:F$42,0) -> 8 | H12: =C12 -> 0.60235362 | I12: =D12 -> 0.86 | J12: =E12 -> 0.81226935 | K12: =ROUND(Notes!$B$4*I12+Notes!$B$5*H12+Notes!$B$6*J12,4) -> 0.7468 | L12: =RANK(K12,K$5:K$42,0) -> 8
A13: France | B13: FRA | C13: =0.547953910556565 -> 0.54795391 | D13: =0.880275603755891 -> 0.8802756 | E13: =0.869865253929667 -> 0.86986525 | F13: =ROUND(Notes!$B$4*D13+Notes!$B$5*C13+Notes!$B$6*E13,4) -> 0.7419 | G13: =RANK(F13,F$5:F$42,0) -> 9 | H13: =C13 -> 0.54795391 | I13: =D13 -> 0.8802756 | J13: =E13 -> 0.86986525 | K13: =ROUND(Notes!$B$4*I13+Notes!$B$5*H13+Notes!$B$6*J13,4) -> 0.7419 | L13: =RANK(K13,K$5:K$42,0) -> 9
A14: Switzerland | B14: CHE | C14: =0.554838709677419 -> 0.55483871 | D14: =0.86 -> 0.86 | E14: =0.905263157894737 -> 0.90526316 | F14: =ROUND(Notes!$B$4*D14+Notes!$B$5*C14+Notes!$B$6*E14,4) -> 0.7411 | G14: =RANK(F14,F$5:F$42,0) -> 10 | H14: =C14 -> 0.55483871 | I14: =D14 -> 0.86 | J14: =E14 -> 0.90526316 | K14: =ROUND(Notes!$B$4*I14+Notes!$B$5*H14+Notes!$B$6*J14,4) -> 0.7411 | L14: =RANK(K14,K$5:K$42,0) -> 10
A15: Slovakia | B15: SVK | C15: =0.547953910556565 -> 0.54795391 | D15: =0.873879108036537 -> 0.87387911 | E15: =0.869865253929667 -> 0.86986525 | F15: =ROUND(Notes!$B$4*D15+Notes!$B$5*C15+Notes!$B$6*E15,4) -> 0.7391 | G15: =RANK(F15,F$5:F$42,0) -> 11 | H15: =C15 -> 0.54795391 | I15: =D15 -> 0.87387911 | J15: =E15 -> 0.86986525 | K15: =ROUND(Notes!$B$4*I15+Notes!$B$5*H15+Notes!$B$6*J15,4) -> 0.7391 | L15: =RANK(K15,K$5:K$42,0) -> 11
A16: Belgium | B16: BEL | C16: =0.547953910556565 -> 0.54795391 | D16: =0.869865253929667 -> 0.86986525 | E16: =0.869865253929667 -> 0.86986525 | F16: =ROUND(Notes!$B$4*D16+Notes!$B$5*C16+Notes!$B$6*E16,4) -> 0.7373 | G16: =RANK(F16,F$5:F$42,0) -> 12 | H16: =C16 -> 0.54795391 | I16: =D16 -> 0.86986525 | J16: =E16 -> 0.86986525 | K16: =ROUND(Notes!$B$4*I16+Notes!$B$5*H16+Notes!$B$6*J16,4) -> 0.7373 | L16: =RANK(K16,K$5:K$42,0) -> 12
A17: Czech Republic | B17: CZE | C17: =0.543222830616488 -> 0.54322283 | D17: =0.873879108036537 -> 0.87387911 | E17: =0.841318847888109 -> 0.84131885 | F17: =ROUND(Notes!$B$4*D17+Notes!$B$5*C17+Notes!$B$6*E17,4) -> 0.7329 | G17: =RANK(F17,F$5:F$42,0) -> 13 | H17: =C17 -> 0.54322283 | I17: =D17 -> 0.87387911 | J17: =E17 -> 0.84131885 | K17: =ROUND(Notes!$B$4*I17+Notes!$B$5*H17+Notes!$B$6*J17,4) -> 0.7329 | L17: =RANK(K17,K$5:K$42,0) -> 13
A18: Mexico | B18: MEX | C18: =0.630382676079967 -> 0.63038268 | D18: =0.795219524916135 -> 0.79521952 | E18: =0.795219524916135 -> 0.79521952 | F18: =ROUND(Notes!$B$4*D18+Notes!$B$5*C18+Notes!$B$6*E18,4) -> 0.7274 | G18: =RANK(F18,F$5:F$42,0) -> 14 | H18: =C18 -> 0.63038268 | I18: =D18 -> 0.79521952 | J18: =E18 -> 0.79521952 | K18: =ROUND(Notes!$B$4*I18+Notes!$B$5*H18+Notes!$B$6*J18,4) -> 0.7274 | L18: =RANK(K18,K$5:K$42,0) -> 14
A19: United Kingdom | B19: GBR | C19: =0.391406012913837 -> 0.39140601 | D19: =1 -> 1 | E19: =0.826923076923077 -> 0.82692308 | F19: =ROUND(Notes!$B$4*D19+Notes!$B$5*C19+Notes!$B$6*E19,4) -> 0.7236 | G19: =RANK(F19,F$5:F$42,0) -> 15 | H19: =C19 -> 0.39140601 | I19: =D19 -> 1 | J19: =E19 -> 0.82692308 | K19: =ROUND(Notes!$B$4*I19+Notes!$B$5*H19+Notes!$B$6*J19,4) -> 0.7236 | L19: =RANK(K19,K$5:K$42,0) -> 15
A20: Israel | B20: ISR | C20: =0.478865241362287 -> 0.47886524 | D20: =0.901030024355631 -> 0.90103002 | E20: =0.835370889649727 -> 0.83537089 | F20: =ROUND(Notes!$B$4*D20+Notes!$B$5*C20+Notes!$B$6*E20,4) -> 0.7174 | G20: =RANK(F20,F$5:F$42,0) -> 16 | H20: =C20 -> 0.47886524 | I20: =D20 -> 0.90103002 | J20: =E20 -> 0.83537089 | K20: =ROUND(Notes!$B$4*I20+Notes!$B$5*H20+Notes!$B$6*J20,4) -> 0.7174 | L20: =RANK(K20,K$5:K$42,0) -> 16
A21: Luxembourg | B21: LUX | C21: =0.479318672008477 -> 0.47931867 | D21: =0.873417350634541 -> 0.87341735 | E21: =0.869865253929667 -> 0.86986525 | F21: =ROUND(Notes!$B$4*D21+Notes!$B$5*C21+Notes!$B$6*E21,4) -> 0.7107 | G21: =RANK(F21,F$5:F$42,0) -> 17 | H21: =C21 -> 0.47931867 | I21: =D21 -> 0.87341735 | J21: =E21 -> 0.86986525 | K21: =ROUND(Notes!$B$4*I21+Notes!$B$5*H21+Notes!$B$6*J21,4) -> 0.7107 | L21: =RANK(K21,K$5:K$42,0) -> 17
A22: Sweden | B22: SWE | C22: =0.479318672008477 -> 0.47931867 | D22: =0.86 -> 0.86 | E22: =0.86 -> 0.86 | F22: =ROUND(Notes!$B$4*D22+Notes!$B$5*C22+Notes!$B$6*E22,4) -> 0.7033 | G22: =RANK(F22,F$5:F$42,0) -> 18 | H22: =C22 -> 0.47931867 | I22: =D22 -> 0.86 | J22: =E22 -> 0.86 | K22: =ROUND(Notes!$B$4*I22+Notes!$B$5*H22+Notes!$B$6*J22,4) -> 0.7033 | L22: =RANK(K22,K$5:K$42,0) -> 18
A23: Portugal | B23: PRT | C23: =0.547953910556565 -> 0.54795391 | D23: =0.888411247396436 -> 0.88841125 | E23: =0.547953910556565 -> 0.54795391 | F23: =ROUND(Notes!$B$4*D23+Notes!$B$5*C23+Notes!$B$6*E23,4) -> 0.6975 | G23: =RANK(F23,F$5:F$42,0) -> 19 | H23: =C23 -> 0.54795391 | I23: =D23 -> 0.88841125 | J23: =E23 -> 0.54795391 | K23: =ROUND(Notes!$B$4*I23+Notes!$B$5*H23+Notes!$B$6*J23,4) -> 0.6975 | L23: =RANK(K23,K$5:K$42,0) -> 19
A24: Finland | B24: FIN | C24: =0.518965517241379 -> 0.51896552 | D24: =0.826923076923077 -> 0.82692308 | E24: =0.737888702767901 -> 0.7378887 | F24: =ROUND(Notes!$B$4*D24+Notes!$B$5*C24+Notes!$B$6*E24,4) -> 0.6869 | G24: =RANK(F24,F$5:F$42,0) -> 20 | H24: =C24 -> 0.51896552 | I24: =D24 -> 0.82692308 | J24: =E24 -> 0.7378887 | K24: =ROUND(Notes!$B$4*I24+Notes!$B$5*H24+Notes!$B$6*J24,4) -> 0.6869 | L24: =RANK(K24,K$5:K$42,0) -> 20
A25: Germany | B25: DEU | C25: =0.391406012913837 -> 0.39140601 | D25: =0.876514043282575 -> 0.87651404 | E25: =0.869865253929667 -> 0.86986525 | F25: =ROUND(Notes!$B$4*D25+Notes!$B$5*C25+Notes!$B$6*E25,4) -> 0.6758 | G25: =RANK(F25,F$5:F$42,0) -> 21 | H25: =C25 -> 0.39140601 | I25: =D25 -> 0.87651404 | J25: =E25 -> 0.86986525 | K25: =ROUND(Notes!$B$4*I25+Notes!$B$5*H25+Notes!$B$6*J25,4) -> 0.6758 | L25: =RANK(K25,K$5:K$42,0) -> 21
A26: Austria | B26: AUT | C26: =0.408845614108812 -> 0.40884561 | D26: =0.884365027341364 -> 0.88436503 | E26: =0.737888702767901 -> 0.7378887 | F26: =ROUND(Notes!$B$4*D26+Notes!$B$5*C26+Notes!$B$6*E26,4) -> 0.6668 | G26: =RANK(F26,F$5:F$42,0) -> 22 | H26: =C26 -> 0.40884561 | I26: =D26 -> 0.88436503 | J26: =E26 -> 0.7378887 | K26: =ROUND(Notes!$B$4*I26+Notes!$B$5*H26+Notes!$B$6*J26,4) -> 0.6668 | L26: =RANK(K26,K$5:K$42,0) -> 22
A27: Turkey | B27: TUR | C27: =0.431068736527055 -> 0.43106874 | D27: =0.864149148541634 -> 0.86414915 | E27: =0.69441435606903 -> 0.69441436 | F27: =ROUND(Notes!$B$4*D27+Notes!$B$5*C27+Notes!$B$6*E27,4) -> 0.6605 | G27: =RANK(F27,F$5:F$42,0) -> 23 | H27: =C27 -> 0.43106874 | I27: =D27 -> 0.86414915 | J27: =E27 -> 0.69441436 | K27: =ROUND(Notes!$B$4*I27+Notes!$B$5*H27+Notes!$B$6*J27,4) -> 0.6605 | L27: =RANK(K27,K$5:K$42,0) -> 23
A28: Slovenia | B28: SVN | C28: =0.391406012913837 -> 0.39140601 | D28: =0.869865253929667 -> 0.86986525 | E28: =0.737888702767901 -> 0.7378887 | F28: =ROUND(Notes!$B$4*D28+Notes!$B$5*C28+Notes!$B$6*E28,4) -> 0.6532 | G28: =RANK(F28,F$5:F$42,0) -> 24 | H28: =C28 -> 0.39140601 | I28: =D28 -> 0.86986525 | J28: =E28 -> 0.7378887 | K28: =ROUND(Notes!$B$4*I28+Notes!$B$5*H28+Notes!$B$6*J28,4) -> 0.6532 | L28: =RANK(K28,K$5:K$42,0) -> 24
A29: Australia | B29: AUS | C29: =0.479318672008477 -> 0.47931867 | D29: =0.851484971473245 -> 0.85148497 | E29: =0.547953910556565 -> 0.54795391 | F29: =ROUND(Notes!$B$4*D29+Notes!$B$5*C29+Notes!$B$6*E29,4) -> 0.653 | G29: =RANK(F29,F$5:F$42,0) -> 25 | H29: =C29 -> 0.47931867 | I29: =D29 -> 0.85148497 | J29: =E29 -> 0.54795391 | K29: =ROUND(Notes!$B$4*I29+Notes!$B$5*H29+Notes!$B$6*J29,4) -> 0.653 | L29: =RANK(K29,K$5:K$42,0) -> 25
A30: Denmark | B30: DNK | C30: =0.391406012913837 -> 0.39140601 | D30: =0.826923076923077 -> 0.82692308 | E30: =0.81340644290143 -> 0.81340644 | F30: =ROUND(Notes!$B$4*D30+Notes!$B$5*C30+Notes!$B$6*E30,4) -> 0.6456 | G30: =RANK(F30,F$5:F$42,0) -> 26 | H30: =C30 -> 0.39140601 | I30: =D30 -> 0.82692308 | J30: =E30 -> 0.81340644 | K30: =ROUND(Notes!$B$4*I30+Notes!$B$5*H30+Notes!$B$6*J30,4) -> 0.6456 | L30: =RANK(K30,K$5:K$42,0) -> 26
A31: Ireland | B31: IRL | C31: =0.479318672008477 -> 0.47931867 | D31: =0.787075165170195 -> 0.78707517 | E31: =0.646263719038607 -> 0.64626372 | F31: =ROUND(Notes!$B$4*D31+Notes!$B$5*C31+Notes!$B$6*E31,4) -> 0.6394 | G31: =RANK(F31,F$5:F$42,0) -> 27 | H31: =C31 -> 0.47931867 | I31: =D31 -> 0.78707517 | J31: =E31 -> 0.64626372 | K31: =ROUND(Notes!$B$4*I31+Notes!$B$5*H31+Notes!$B$6*J31,4) -> 0.6394 | L31: =RANK(K31,K$5:K$42,0) -> 27
A32: Greece | B32: GRC | C32: =0.479318672008477 -> 0.47931867 | D32: =0.737888702767901 -> 0.7378887 | E32: =0.737888702767901 -> 0.7378887 | F32: =ROUND(Notes!$B$4*D32+Notes!$B$5*C32+Notes!$B$6*E32,4) -> 0.6314 | G32: =RANK(F32,F$5:F$42,0) -> 28 | H32: =C32 -> 0.47931867 | I32: =D32 -> 0.7378887 | J32: =E32 -> 0.7378887 | K32: =ROUND(Notes!$B$4*I32+Notes!$B$5*H32+Notes!$B$6*J32,4) -> 0.6314 | L32: =RANK(K32,K$5:K$42,0) -> 28
A33: Netherlands | B33: NLD | C33: =0.338474732816403 -> 0.33847473 | D33: =0.813463195231154 -> 0.8134632 | E33: =0.869865253929667 -> 0.86986525 | F33: =ROUND(Notes!$B$4*D33+Notes!$B$5*C33+Notes!$B$6*E33,4) -> 0.6263 | G33: =RANK(F33,F$5:F$42,0) -> 29 | H33: =C33 -> 0.33847473 | I33: =D33 -> 0.8134632 | J33: =E33 -> 0.86986525 | K33: =ROUND(Notes!$B$4*I33+Notes!$B$5*H33+Notes!$B$6*J33,4) -> 0.6263 | L33: =RANK(K33,K$5:K$42,0) -> 29
A34: Spain | B34: ESP | C34: =0.391406012913837 -> 0.39140601 | D34: =0.778563038959402 -> 0.77856304 | E34: =0.737888702767901 -> 0.7378887 | F34: =ROUND(Notes!$B$4*D34+Notes!$B$5*C34+Notes!$B$6*E34,4) -> 0.6131 | G34: =RANK(F34,F$5:F$42,0) -> 30 | H34: =C34 -> 0.39140601 | I34: =D34 -> 0.77856304 | J34: =E34 -> 0.7378887 | K34: =ROUND(Notes!$B$4*I34+Notes!$B$5*H34+Notes!$B$6*J34,4) -> 0.6131 | L34: =RANK(K34,K$5:K$42,0) -> 30
A35: Japan | B35: JPN | C35: =0.278958448750364 -> 0.27895845 | D35: =0.859028659709284 -> 0.85902866 | E35: =0.787075165170195 -> 0.78707517 | F35: =ROUND(Notes!$B$4*D35+Notes!$B$5*C35+Notes!$B$6*E35,4) -> 0.6095 | G35: =RANK(F35,F$5:F$42,0) -> 31 | H35: =C35 -> 0.27895845 | I35: =D35 -> 0.85902866 | J35: =E35 -> 0.78707517 | K35: =ROUND(Notes!$B$4*I35+Notes!$B$5*H35+Notes!$B$6*J35,4) -> 0.6095 | L35: =RANK(K35,K$5:K$42,0) -> 31
A36: Norway | B36: NOR | C36: =0.373913043478261 -> 0.37391304 | D36: =0.781818181818182 -> 0.78181818 | E36: =0.737888702767901 -> 0.7378887 | F36: =ROUND(Notes!$B$4*D36+Notes!$B$5*C36+Notes!$B$6*E36,4) -> 0.6073 | G36: =RANK(F36,F$5:F$42,0) -> 32 | H36: =C36 -> 0.37391304 | I36: =D36 -> 0.78181818 | J36: =E36 -> 0.7378887 | K36: =ROUND(Notes!$B$4*I36+Notes!$B$5*H36+Notes!$B$6*J36,4) -> 0.6073 | L36: =RANK(K36,K$5:K$42,0) -> 32
A37: Poland | B37: POL | C37: =0.338474732816403 -> 0.33847473 | D37: =0.737888702767901 -> 0.7378887 | E37: =0.869865253929667 -> 0.86986525 | F37: =ROUND(Notes!$B$4*D37+Notes!$B$5*C37+Notes!$B$6*E37,4) -> 0.5932 | G37: =RANK(F37,F$5:F$42,0) -> 33 | H37: =C37 -> 0.33847473 | I37: =D37 -> 0.7378887 | J37: =E37 -> 0.86986525 | K37: =ROUND(Notes!$B$4*I37+Notes!$B$5*H37+Notes!$B$6*J37,4) -> 0.5932 | L37: =RANK(K37,K$5:K$42,0) -> 33
A38: Costa Rica | B38: CRI | C38: =0.278958448750364 -> 0.27895845 | D38: =0.822456690745778 -> 0.82245669 | E38: =0.737888702767901 -> 0.7378887 | F38: =ROUND(Notes!$B$4*D38+Notes!$B$5*C38+Notes!$B$6*E38,4) -> 0.5861 | G38: =RANK(F38,F$5:F$42,0) -> 34 | H38: =C38 -> 0.27895845 | I38: =D38 -> 0.82245669 | J38: =E38 -> 0.7378887 | K38: =ROUND(Notes!$B$4*I38+Notes!$B$5*H38+Notes!$B$6*J38,4) -> 0.5861 | L38: =RANK(K38,K$5:K$42,0) -> 34
A39: Hungary | B39: HUN | C39: =0.278958448750364 -> 0.27895845 | D39: =0.816200383417959 -> 0.81620038 | E39: =0.737888702767901 -> 0.7378887 | F39: =ROUND(Notes!$B$4*D39+Notes!$B$5*C39+Notes!$B$6*E39,4) -> 0.5834 | G39: =RANK(F39,F$5:F$42,0) -> 35 | H39: =C39 -> 0.27895845 | I39: =D39 -> 0.81620038 | J39: =E39 -> 0.7378887 | K39: =ROUND(Notes!$B$4*I39+Notes!$B$5*H39+Notes!$B$6*J39,4) -> 0.5834 | L39: =RANK(K39,K$5:K$42,0) -> 35
A40: Colombia | B40: COL | C40: =0.305956530933891 -> 0.30595653 | D40: =0.737888702767901 -> 0.7378887 | E40: =0.869865253929667 -> 0.86986525 | F40: =ROUND(Notes!$B$4*D40+Notes!$B$5*C40+Notes!$B$6*E40,4) -> 0.5798 | G40: =RANK(F40,F$5:F$42,0) -> 36 | H40: =C40 -> 0.30595653 | I40: =D40 -> 0.7378887 | J40: =E40 -> 0.86986525 | K40: =ROUND(Notes!$B$4*I40+Notes!$B$5*H40+Notes!$B$6*J40,4) -> 0.5798 | L40: =RANK(K40,K$5:K$42,0) -> 36
A41: New Zealand | B41: NZL | C41: =0.2 -> 0.2 | D41: =0.74468085106383 -> 0.74468085 | E41: =0.547953910556565 -> 0.54795391 | F41: =ROUND(Notes!$B$4*D41+Notes!$B$5*C41+Notes!$B$6*E41,4) -> 0.4911 | G41: =RANK(F41,F$5:F$42,0) -> 37 | H41: =C41 -> 0.2 | I41: =D41 -> 0.74468085 | J41: =E41 -> 0.54795391 | K41: =ROUND(Notes!$B$4*I41+Notes!$B$5*H41+Notes!$B$6*J41,4) -> 0.4911 | L41: =RANK(K41,K$5:K$42,0) -> 37
A42: Chile | B42: CHL | C42: =0.42321653857669 -> 0.42321654 | D42: =0.705977756078566 -> 0.70597776 | E42: =0 -> 0 | F42: =ROUND(Notes!$B$4*D42+Notes!$B$5*C42+Notes!$B$6*E42,4) -> 0.4842 | G42: =RANK(F42,F$5:F$42,0) -> 38 | H42: =C42 -> 0.42321654 | I42: =D42 -> 0.70597776 | J42: =E42 -> 0 | K42: =ROUND(Notes!$B$4*I42+Notes!$B$5*H42+Notes!$B$6*J42,4) -> 0.4842 | L42: =RANK(K42,K$5:K$42,0) -> 38

Sheet 2027
A1: Net Present Value of Capital Allowances, OECD Ranking 2027: current law vs. Canada immediate-expensing reform
A2: Weighted avg = weights (Notes) applied to asset NPVs (source: final-data/npv_all_years.csv). Reform sets Canada machinery and buildings to 1.0; intangibles unchanged. Ranks: RANK on weighted avg rounded to 4 dp, ties=min.
A4: Country | B4: ISO | C4: Buildings (current law) | D4: Machinery (current law) | E4: Intangibles (current law) | F4: Weighted avg (current law) | G4: Rank (current law) | H4: Buildings (reform) | I4: Machinery (reform) | J4: Intangibles (reform) | K4: Weighted avg (reform) | L4: Rank (reform)
A5: Estonia | B5: EST | C5: =1 -> 1 | D5: =1 -> 1 | E5: =1 -> 1 | F5: =ROUND(Notes!$B$4*D5+Notes!$B$5*C5+Notes!$B$6*E5,4) -> 1 | G5: =RANK(F5,F$5:F$42,0) -> 1 | H5: =C5 -> 1 | I5: =D5 -> 1 | J5: =E5 -> 1 | K5: =ROUND(Notes!$B$4*I5+Notes!$B$5*H5+Notes!$B$6*J5,4) -> 1 | L5: =RANK(K5,K$5:K$42,0) -> 1
A6: Latvia | B6: LVA | C6: =1 -> 1 | D6: =1 -> 1 | E6: =1 -> 1 | F6: =ROUND(Notes!$B$4*D6+Notes!$B$5*C6+Notes!$B$6*E6,4) -> 1 | G6: =RANK(F6,F$5:F$42,0) -> 1 | H6: =C6 -> 1 | I6: =D6 -> 1 | J6: =E6 -> 1 | K6: =ROUND(Notes!$B$4*I6+Notes!$B$5*H6+Notes!$B$6*J6,4) -> 1 | L6: =RANK(K6,K$5:K$42,0) -> 1
A7: United States | B7: USA | C7: =1 -> 1 | D7: =1 -> 1 | E7: =0.632751338890881 -> 0.63275134 | F7: =ROUND(Notes!$B$4*D7+Notes!$B$5*C7+Notes!$B$6*E7,4) -> 0.9452 | G7: =RANK(F7,F$5:F$42,0) -> 3 | H7: =C7 -> 1 | I7: =D7 -> 1 | J7: =E7 -> 0.63275134 | K7: =ROUND(Notes!$B$4*I7+Notes!$B$5*H7+Notes!$B$6*J7,4) -> 0.9452 | L7: =RANK(K7,K$5:K$42,0) -> 3
A8: Lithuania | B8: LTU | C8: =0.826923076923077 -> 0.82692308 | D8: =1 -> 1 | E8: =1 -> 1 | F8: =ROUND(Notes!$B$4*D8+Notes!$B$5*C8+Notes!$B$6*E8,4) -> 0.9288 | G8: =RANK(F8,F$5:F$42,0) -> 4 | H8: =C8 -> 0.82692308 | I8: =D8 -> 1 | J8: =E8 -> 1 | K8: =ROUND(Notes!$B$4*I8+Notes!$B$5*H8+Notes!$B$6*J8,4) -> 0.9288 | L8: =RANK(K8,K$5:K$42,0) -> 4
A9: Canada | B9: CAN | C9: =0.635714285714286 -> 0.63571429 | D9: =1 -> 1 | E9: =0.43 -> 0.43 | F9: =ROUND(Notes!$B$4*D9+Notes!$B$5*C9+Notes!$B$6*E9,4) -> 0.765 | G9: =RANK(F9,F$5:F$42,0) -> 5 | H9: =1 -> 1 | I9: =1 -> 1 | J9: =E9 -> 0.43 | K9: =ROUND(Notes!$B$4*I9+Notes!$B$5*H9+Notes!$B$6*J9,4) -> 0.9149 | L9: =RANK(K9,K$5:K$42,0) -> 5
A10: Italy | B10: ITA | C10: =0.576669379707147 -> 0.57666938 | D10: =0.869865253929667 -> 0.86986525 | E10: =0.965116279069767 -> 0.96511628 | F10: =ROUND(Notes!$B$4*D10+Notes!$B$5*C10+Notes!$B$6*E10,4) -> 0.7634 | G10: =RANK(F10,F$5:F$42,0) -> 6 | H10: =C10 -> 0.57666938 | I10: =D10 -> 0.86986525 | J10: =E10 -> 0.96511628 | K10: =ROUND(Notes!$B$4*I10+Notes!$B$5*H10+Notes!$B$6*J10,4) -> 0.7634 | L10: =RANK(K10,K$5:K$42,0) -> 6
A11: Korea | B11: KOR | C11: =0.547953910556565 -> 0.54795391 | D11: =0.921720532319392 -> 0.92172053 | E11: =0.813463195231154 -> 0.8134632 | F11: =ROUND(Notes!$B$4*D11+Notes!$B$5*C11+Notes!$B$6*E11,4) -> 0.7517 | G11: =RANK(F11,F$5:F$42,0) -> 7 | H11: =C11 -> 0.54795391 | I11: =D11 -> 0.92172053 | J11: =E11 -> 0.8134632 | K11: =ROUND(Notes!$B$4*I11+Notes!$B$5*H11+Notes!$B$6*J11,4) -> 0.7517 | L11: =RANK(K11,K$5:K$42,0) -> 7
A12: Iceland | B12: ISL | C12: =0.602353618717047 -> 0.60235362 | D12: =0.86 -> 0.86 | E12: =0.812269350072009 -> 0.81226935 | F12: =ROUND(Notes!$B$4*D12+Notes!$B$5*C12+Notes!$B$6*E12,4) -> 0.7468 | G12: =RANK(F12,F$5:F$42,0) -> 8 | H12: =C12 -> 0.60235362 | I12: =D12 -> 0.86 | J12: =E12 -> 0.81226935 | K12: =ROUND(Notes!$B$4*I12+Notes!$B$5*H12+Notes!$B$6*J12,4) -> 0.7468 | L12: =RANK(K12,K$5:K$42,0) -> 8
A13: France | B13: FRA | C13: =0.547953910556565 -> 0.54795391 | D13: =0.880275603755891 -> 0.8802756 | E13: =0.869865253929667 -> 0.86986525 | F13: =ROUND(Notes!$B$4*D13+Notes!$B$5*C13+Notes!$B$6*E13,4) -> 0.7419 | G13: =RANK(F13,F$5:F$42,0) -> 9 | H13: =C13 -> 0.54795391 | I13: =D13 -> 0.8802756 | J13: =E13 -> 0.86986525 | K13: =ROUND(Notes!$B$4*I13+Notes!$B$5*H13+Notes!$B$6*J13,4) -> 0.7419 | L13: =RANK(K13,K$5:K$42,0) -> 9
A14: Switzerland | B14: CHE | C14: =0.554838709677419 -> 0.55483871 | D14: =0.86 -> 0.86 | E14: =0.905263157894737 -> 0.90526316 | F14: =ROUND(Notes!$B$4*D14+Notes!$B$5*C14+Notes!$B$6*E14,4) -> 0.7411 | G14: =RANK(F14,F$5:F$42,0) -> 10 | H14: =C14 -> 0.55483871 | I14: =D14 -> 0.86 | J14: =E14 -> 0.90526316 | K14: =ROUND(Notes!$B$4*I14+Notes!$B$5*H14+Notes!$B$6*J14,4) -> 0.7411 | L14: =RANK(K14,K$5:K$42,0) -> 10
A15: Slovakia | B15: SVK | C15: =0.547953910556565 -> 0.54795391 | D15: =0.873879108036537 -> 0.87387911 | E15: =0.869865253929667 -> 0.86986525 | F15: =ROUND(Notes!$B$4*D15+Notes!$B$5*C15+Notes!$B$6*E15,4) -> 0.7391 | G15: =RANK(F15,F$5:F$42,0) -> 11 | H15: =C15 -> 0.54795391 | I15: =D15 -> 0.87387911 | J15: =E15 -> 0.86986525 | K15: =ROUND(Notes!$B$4*I15+Notes!$B$5*H15+Notes!$B$6*J15,4) -> 0.7391 | L15: =RANK(K15,K$5:K$42,0) -> 11
A16: Belgium | B16: BEL | C16: =0.547953910556565 -> 0.54795391 | D16: =0.869865253929667 -> 0.86986525 | E16: =0.869865253929667 -> 0.86986525 | F16: =ROUND(Notes!$B$4*D16+Notes!$B$5*C16+Notes!$B$6*E16,4) -> 0.7373 | G16: =RANK(F16,F$5:F$42,0) -> 12 | H16: =C16 -> 0.54795391 | I16: =D16 -> 0.86986525 | J16: =E16 -> 0.86986525 | K16: =ROUND(Notes!$B$4*I16+Notes!$B$5*H16+Notes!$B$6*J16,4) -> 0.7373 | L16: =RANK(K16,K$5:K$42,0) -> 12
A17: Czech Republic | B17: CZE | C17: =0.543222830616488 -> 0.54322283 | D17: =0.873879108036537 -> 0.87387911 | E17: =0.841318847888109 -> 0.84131885 | F17: =ROUND(Notes!$B$4*D17+Notes!$B$5*C17+Notes!$B$6*E17,4) -> 0.7329 | G17: =RANK(F17,F$5:F$42,0) -> 13 | H17: =C17 -> 0.54322283 | I17: =D17 -> 0.87387911 | J17: =E17 -> 0.84131885 | K17: =ROUND(Notes!$B$4*I17+Notes!$B$5*H17+Notes!$B$6*J17,4) -> 0.7329 | L17: =RANK(K17,K$5:K$42,0) -> 13
A18: Mexico | B18: MEX | C18: =0.630382676079967 -> 0.63038268 | D18: =0.795219524916135 -> 0.79521952 | E18: =0.795219524916135 -> 0.79521952 | F18: =ROUND(Notes!$B$4*D18+Notes!$B$5*C18+Notes!$B$6*E18,4) -> 0.7274 | G18: =RANK(F18,F$5:F$42,0) -> 14 | H18: =C18 -> 0.63038268 | I18: =D18 -> 0.79521952 | J18: =E18 -> 0.79521952 | K18: =ROUND(Notes!$B$4*I18+Notes!$B$5*H18+Notes!$B$6*J18,4) -> 0.7274 | L18: =RANK(K18,K$5:K$42,0) -> 14
A19: United Kingdom | B19: GBR | C19: =0.391406012913837 -> 0.39140601 | D19: =1 -> 1 | E19: =0.826923076923077 -> 0.82692308 | F19: =ROUND(Notes!$B$4*D19+Notes!$B$5*C19+Notes!$B$6*E19,4) -> 0.7236 | G19: =RANK(F19,F$5:F$42,0) -> 15 | H19: =C19 -> 0.39140601 | I19: =D19 -> 1 | J19: =E19 -> 0.82692308 | K19: =ROUND(Notes!$B$4*I19+Notes!$B$5*H19+Notes!$B$6*J19,4) -> 0.7236 | L19: =RANK(K19,K$5:K$42,0) -> 15
A20: Israel | B20: ISR | C20: =0.478865241362287 -> 0.47886524 | D20: =0.901030024355631 -> 0.90103002 | E20: =0.835370889649727 -> 0.83537089 | F20: =ROUND(Notes!$B$4*D20+Notes!$B$5*C20+Notes!$B$6*E20,4) -> 0.7174 | G20: =RANK(F20,F$5:F$42,0) -> 16 | H20: =C20 -> 0.47886524 | I20: =D20 -> 0.90103002 | J20: =E20 -> 0.83537089 | K20: =ROUND(Notes!$B$4*I20+Notes!$B$5*H20+Notes!$B$6*J20,4) -> 0.7174 | L20: =RANK(K20,K$5:K$42,0) -> 16
A21: Luxembourg | B21: LUX | C21: =0.479318672008477 -> 0.47931867 | D21: =0.873417350634541 -> 0.87341735 | E21: =0.869865253929667 -> 0.86986525 | F21: =ROUND(Notes!$B$4*D21+Notes!$B$5*C21+Notes!$B$6*E21,4) -> 0.7107 | G21: =RANK(F21,F$5:F$42,0) -> 17 | H21: =C21 -> 0.47931867 | I21: =D21 -> 0.87341735 | J21: =E21 -> 0.86986525 | K21: =ROUND(Notes!$B$4*I21+Notes!$B$5*H21+Notes!$B$6*J21,4) -> 0.7107 | L21: =RANK(K21,K$5:K$42,0) -> 17
A22: Sweden | B22: SWE | C22: =0.479318672008477 -> 0.47931867 | D22: =0.86 -> 0.86 | E22: =0.86 -> 0.86 | F22: =ROUND(Notes!$B$4*D22+Notes!$B$5*C22+Notes!$B$6*E22,4) -> 0.7033 | G22: =RANK(F22,F$5:F$42,0) -> 18 | H22: =C22 -> 0.47931867 | I22: =D22 -> 0.86 | J22: =E22 -> 0.86 | K22: =ROUND(Notes!$B$4*I22+Notes!$B$5*H22+Notes!$B$6*J22,4) -> 0.7033 | L22: =RANK(K22,K$5:K$42,0) -> 18
A23: Portugal | B23: PRT | C23: =0.547953910556565 -> 0.54795391 | D23: =0.888411247396436 -> 0.88841125 | E23: =0.547953910556565 -> 0.54795391 | F23: =ROUND(Notes!$B$4*D23+Notes!$B$5*C23+Notes!$B$6*E23,4) -> 0.6975 | G23: =RANK(F23,F$5:F$42,0) -> 19 | H23: =C23 -> 0.54795391 | I23: =D23 -> 0.88841125 | J23: =E23 -> 0.54795391 | K23: =ROUND(Notes!$B$4*I23+Notes!$B$5*H23+Notes!$B$6*J23,4) -> 0.6975 | L23: =RANK(K23,K$5:K$42,0) -> 19
A24: Finland | B24: FIN | C24: =0.518965517241379 -> 0.51896552 | D24: =0.826923076923077 -> 0.82692308 | E24: =0.737888702767901 -> 0.7378887 | F24: =ROUND(Notes!$B$4*D24+Notes!$B$5*C24+Notes!$B$6*E24,4) -> 0.6869 | G24: =RANK(F24,F$5:F$42,0) -> 20 | H24: =C24 -> 0.51896552 | I24: =D24 -> 0.82692308 | J24: =E24 -> 0.7378887 | K24: =ROUND(Notes!$B$4*I24+Notes!$B$5*H24+Notes!$B$6*J24,4) -> 0.6869 | L24: =RANK(K24,K$5:K$42,0) -> 20
A25: Germany | B25: DEU | C25: =0.391406012913837 -> 0.39140601 | D25: =0.876514043282575 -> 0.87651404 | E25: =0.869865253929667 -> 0.86986525 | F25: =ROUND(Notes!$B$4*D25+Notes!$B$5*C25+Notes!$B$6*E25,4) -> 0.6758 | G25: =RANK(F25,F$5:F$42,0) -> 21 | H25: =C25 -> 0.39140601 | I25: =D25 -> 0.87651404 | J25: =E25 -> 0.86986525 | K25: =ROUND(Notes!$B$4*I25+Notes!$B$5*H25+Notes!$B$6*J25,4) -> 0.6758 | L25: =RANK(K25,K$5:K$42,0) -> 21
A26: Austria | B26: AUT | C26: =0.408845614108812 -> 0.40884561 | D26: =0.884365027341364 -> 0.88436503 | E26: =0.737888702767901 -> 0.7378887 | F26: =ROUND(Notes!$B$4*D26+Notes!$B$5*C26+Notes!$B$6*E26,4) -> 0.6668 | G26: =RANK(F26,F$5:F$42,0) -> 22 | H26: =C26 -> 0.40884561 | I26: =D26 -> 0.88436503 | J26: =E26 -> 0.7378887 | K26: =ROUND(Notes!$B$4*I26+Notes!$B$5*H26+Notes!$B$6*J26,4) -> 0.6668 | L26: =RANK(K26,K$5:K$42,0) -> 22
A27: Turkey | B27: TUR | C27: =0.431068736527055 -> 0.43106874 | D27: =0.864149148541634 -> 0.86414915 | E27: =0.69441435606903 -> 0.69441436 | F27: =ROUND(Notes!$B$4*D27+Notes!$B$5*C27+Notes!$B$6*E27,4) -> 0.6605 | G27: =RANK(F27,F$5:F$42,0) -> 23 | H27: =C27 -> 0.43106874 | I27: =D27 -> 0.86414915 | J27: =E27 -> 0.69441436 | K27: =ROUND(Notes!$B$4*I27+Notes!$B$5*H27+Notes!$B$6*J27,4) -> 0.6605 | L27: =RANK(K27,K$5:K$42,0) -> 23
A28: Slovenia | B28: SVN | C28: =0.391406012913837 -> 0.39140601 | D28: =0.869865253929667 -> 0.86986525 | E28: =0.737888702767901 -> 0.7378887 | F28: =ROUND(Notes!$B$4*D28+Notes!$B$5*C28+Notes!$B$6*E28,4) -> 0.6532 | G28: =RANK(F28,F$5:F$42,0) -> 24 | H28: =C28 -> 0.39140601 | I28: =D28 -> 0.86986525 | J28: =E28 -> 0.7378887 | K28: =ROUND(Notes!$B$4*I28+Notes!$B$5*H28+Notes!$B$6*J28,4) -> 0.6532 | L28: =RANK(K28,K$5:K$42,0) -> 24
A29: Australia | B29: AUS | C29: =0.479318672008477 -> 0.47931867 | D29: =0.851484971473245 -> 0.85148497 | E29: =0.547953910556565 -> 0.54795391 | F29: =ROUND(Notes!$B$4*D29+Notes!$B$5*C29+Notes!$B$6*E29,4) -> 0.653 | G29: =RANK(F29,F$5:F$42,0) -> 25 | H29: =C29 -> 0.47931867 | I29: =D29 -> 0.85148497 | J29: =E29 -> 0.54795391 | K29: =ROUND(Notes!$B$4*I29+Notes!$B$5*H29+Notes!$B$6*J29,4) -> 0.653 | L29: =RANK(K29,K$5:K$42,0) -> 25
A30: Denmark | B30: DNK | C30: =0.391406012913837 -> 0.39140601 | D30: =0.826923076923077 -> 0.82692308 | E30: =0.81340644290143 -> 0.81340644 | F30: =ROUND(Notes!$B$4*D30+Notes!$B$5*C30+Notes!$B$6*E30,4) -> 0.6456 | G30: =RANK(F30,F$5:F$42,0) -> 26 | H30: =C30 -> 0.39140601 | I30: =D30 -> 0.82692308 | J30: =E30 -> 0.81340644 | K30: =ROUND(Notes!$B$4*I30+Notes!$B$5*H30+Notes!$B$6*J30,4) -> 0.6456 | L30: =RANK(K30,K$5:K$42,0) -> 26
A31: Ireland | B31: IRL | C31: =0.479318672008477 -> 0.47931867 | D31: =0.787075165170195 -> 0.78707517 | E31: =0.646263719038607 -> 0.64626372 | F31: =ROUND(Notes!$B$4*D31+Notes!$B$5*C31+Notes!$B$6*E31,4) -> 0.6394 | G31: =RANK(F31,F$5:F$42,0) -> 27 | H31: =C31 -> 0.47931867 | I31: =D31 -> 0.78707517 | J31: =E31 -> 0.64626372 | K31: =ROUND(Notes!$B$4*I31+Notes!$B$5*H31+Notes!$B$6*J31,4) -> 0.6394 | L31: =RANK(K31,K$5:K$42,0) -> 27
A32: Greece | B32: GRC | C32: =0.479318672008477 -> 0.47931867 | D32: =0.737888702767901 -> 0.7378887 | E32: =0.737888702767901 -> 0.7378887 | F32: =ROUND(Notes!$B$4*D32+Notes!$B$5*C32+Notes!$B$6*E32,4) -> 0.6314 | G32: =RANK(F32,F$5:F$42,0) -> 28 | H32: =C32 -> 0.47931867 | I32: =D32 -> 0.7378887 | J32: =E32 -> 0.7378887 | K32: =ROUND(Notes!$B$4*I32+Notes!$B$5*H32+Notes!$B$6*J32,4) -> 0.6314 | L32: =RANK(K32,K$5:K$42,0) -> 28
A33: Netherlands | B33: NLD | C33: =0.338474732816403 -> 0.33847473 | D33: =0.813463195231154 -> 0.8134632 | E33: =0.869865253929667 -> 0.86986525 | F33: =ROUND(Notes!$B$4*D33+Notes!$B$5*C33+Notes!$B$6*E33,4) -> 0.6263 | G33: =RANK(F33,F$5:F$42,0) -> 29 | H33: =C33 -> 0.33847473 | I33: =D33 -> 0.8134632 | J33: =E33 -> 0.86986525 | K33: =ROUND(Notes!$B$4*I33+Notes!$B$5*H33+Notes!$B$6*J33,4) -> 0.6263 | L33: =RANK(K33,K$5:K$42,0) -> 29
A34: Spain | B34: ESP | C34: =0.391406012913837 -> 0.39140601 | D34: =0.778563038959402 -> 0.77856304 | E34: =0.737888702767901 -> 0.7378887 | F34: =ROUND(Notes!$B$4*D34+Notes!$B$5*C34+Notes!$B$6*E34,4) -> 0.6131 | G34: =RANK(F34,F$5:F$42,0) -> 30 | H34: =C34 -> 0.39140601 | I34: =D34 -> 0.77856304 | J34: =E34 -> 0.7378887 | K34: =ROUND(Notes!$B$4*I34+Notes!$B$5*H34+Notes!$B$6*J34,4) -> 0.6131 | L34: =RANK(K34,K$5:K$42,0) -> 30
A35: Japan | B35: JPN | C35: =0.278958448750364 -> 0.27895845 | D35: =0.859028659709284 -> 0.85902866 | E35: =0.787075165170195 -> 0.78707517 | F35: =ROUND(Notes!$B$4*D35+Notes!$B$5*C35+Notes!$B$6*E35,4) -> 0.6095 | G35: =RANK(F35,F$5:F$42,0) -> 31 | H35: =C35 -> 0.27895845 | I35: =D35 -> 0.85902866 | J35: =E35 -> 0.78707517 | K35: =ROUND(Notes!$B$4*I35+Notes!$B$5*H35+Notes!$B$6*J35,4) -> 0.6095 | L35: =RANK(K35,K$5:K$42,0) -> 31
A36: Norway | B36: NOR | C36: =0.373913043478261 -> 0.37391304 | D36: =0.781818181818182 -> 0.78181818 | E36: =0.737888702767901 -> 0.7378887 | F36: =ROUND(Notes!$B$4*D36+Notes!$B$5*C36+Notes!$B$6*E36,4) -> 0.6073 | G36: =RANK(F36,F$5:F$42,0) -> 32 | H36: =C36 -> 0.37391304 | I36: =D36 -> 0.78181818 | J36: =E36 -> 0.7378887 | K36: =ROUND(Notes!$B$4*I36+Notes!$B$5*H36+Notes!$B$6*J36,4) -> 0.6073 | L36: =RANK(K36,K$5:K$42,0) -> 32
A37: Poland | B37: POL | C37: =0.338474732816403 -> 0.33847473 | D37: =0.737888702767901 -> 0.7378887 | E37: =0.869865253929667 -> 0.86986525 | F37: =ROUND(Notes!$B$4*D37+Notes!$B$5*C37+Notes!$B$6*E37,4) -> 0.5932 | G37: =RANK(F37,F$5:F$42,0) -> 33 | H37: =C37 -> 0.33847473 | I37: =D37 -> 0.7378887 | J37: =E37 -> 0.86986525 | K37: =ROUND(Notes!$B$4*I37+Notes!$B$5*H37+Notes!$B$6*J37,4) -> 0.5932 | L37: =RANK(K37,K$5:K$42,0) -> 33
A38: Costa Rica | B38: CRI | C38: =0.278958448750364 -> 0.27895845 | D38: =0.822456690745778 -> 0.82245669 | E38: =0.737888702767901 -> 0.7378887 | F38: =ROUND(Notes!$B$4*D38+Notes!$B$5*C38+Notes!$B$6*E38,4) -> 0.5861 | G38: =RANK(F38,F$5:F$42,0) -> 34 | H38: =C38 -> 0.27895845 | I38: =D38 -> 0.82245669 | J38: =E38 -> 0.7378887 | K38: =ROUND(Notes!$B$4*I38+Notes!$B$5*H38+Notes!$B$6*J38,4) -> 0.5861 | L38: =RANK(K38,K$5:K$42,0) -> 34
A39: Hungary | B39: HUN | C39: =0.278958448750364 -> 0.27895845 | D39: =0.816200383417959 -> 0.81620038 | E39: =0.737888702767901 -> 0.7378887 | F39: =ROUND(Notes!$B$4*D39+Notes!$B$5*C39+Notes!$B$6*E39,4) -> 0.5834 | G39: =RANK(F39,F$5:F$42,0) -> 35 | H39: =C39 -> 0.27895845 | I39: =D39 -> 0.81620038 | J39: =E39 -> 0.7378887 | K39: =ROUND(Notes!$B$4*I39+Notes!$B$5*H39+Notes!$B$6*J39,4) -> 0.5834 | L39: =RANK(K39,K$5:K$42,0) -> 35
A40: Colombia | B40: COL | C40: =0.305956530933891 -> 0.30595653 | D40: =0.737888702767901 -> 0.7378887 | E40: =0.869865253929667 -> 0.86986525 | F40: =ROUND(Notes!$B$4*D40+Notes!$B$5*C40+Notes!$B$6*E40,4) -> 0.5798 | G40: =RANK(F40,F$5:F$42,0) -> 36 | H40: =C40 -> 0.30595653 | I40: =D40 -> 0.7378887 | J40: =E40 -> 0.86986525 | K40: =ROUND(Notes!$B$4*I40+Notes!$B$5*H40+Notes!$B$6*J40,4) -> 0.5798 | L40: =RANK(K40,K$5:K$42,0) -> 36
A41: New Zealand | B41: NZL | C41: =0.2 -> 0.2 | D41: =0.74468085106383 -> 0.74468085 | E41: =0.547953910556565 -> 0.54795391 | F41: =ROUND(Notes!$B$4*D41+Notes!$B$5*C41+Notes!$B$6*E41,4) -> 0.4911 | G41: =RANK(F41,F$5:F$42,0) -> 37 | H41: =C41 -> 0.2 | I41: =D41 -> 0.74468085 | J41: =E41 -> 0.54795391 | K41: =ROUND(Notes!$B$4*I41+Notes!$B$5*H41+Notes!$B$6*J41,4) -> 0.4911 | L41: =RANK(K41,K$5:K$42,0) -> 37
A42: Chile | B42: CHL | C42: =0.42321653857669 -> 0.42321654 | D42: =0.705977756078566 -> 0.70597776 | E42: =0 -> 0 | F42: =ROUND(Notes!$B$4*D42+Notes!$B$5*C42+Notes!$B$6*E42,4) -> 0.4842 | G42: =RANK(F42,F$5:F$42,0) -> 38 | H42: =C42 -> 0.42321654 | I42: =D42 -> 0.70597776 | J42: =E42 -> 0 | K42: =ROUND(Notes!$B$4*I42+Notes!$B$5*H42+Notes!$B$6*J42,4) -> 0.4842 | L42: =RANK(K42,K$5:K$42,0) -> 38

Sheet 2028
A1: Net Present Value of Capital Allowances, OECD Ranking 2028: current law vs. Canada immediate-expensing reform
A2: Weighted avg = weights (Notes) applied to asset NPVs (source: final-data/npv_all_years.csv). Reform sets Canada machinery and buildings to 1.0; intangibles unchanged. Ranks: RANK on weighted avg rounded to 4 dp, ties=min.
A4: Country | B4: ISO | C4: Buildings (current law) | D4: Machinery (current law) | E4: Intangibles (current law) | F4: Weighted avg (current law) | G4: Rank (current law) | H4: Buildings (reform) | I4: Machinery (reform) | J4: Intangibles (reform) | K4: Weighted avg (reform) | L4: Rank (reform)
A5: Estonia | B5: EST | C5: =1 -> 1 | D5: =1 -> 1 | E5: =1 -> 1 | F5: =ROUND(Notes!$B$4*D5+Notes!$B$5*C5+Notes!$B$6*E5,4) -> 1 | G5: =RANK(F5,F$5:F$42,0) -> 1 | H5: =C5 -> 1 | I5: =D5 -> 1 | J5: =E5 -> 1 | K5: =ROUND(Notes!$B$4*I5+Notes!$B$5*H5+Notes!$B$6*J5,4) -> 1 | L5: =RANK(K5,K$5:K$42,0) -> 1
A6: Latvia | B6: LVA | C6: =1 -> 1 | D6: =1 -> 1 | E6: =1 -> 1 | F6: =ROUND(Notes!$B$4*D6+Notes!$B$5*C6+Notes!$B$6*E6,4) -> 1 | G6: =RANK(F6,F$5:F$42,0) -> 1 | H6: =C6 -> 1 | I6: =D6 -> 1 | J6: =E6 -> 1 | K6: =ROUND(Notes!$B$4*I6+Notes!$B$5*H6+Notes!$B$6*J6,4) -> 1 | L6: =RANK(K6,K$5:K$42,0) -> 1
A7: United States | B7: USA | C7: =1 -> 1 | D7: =1 -> 1 | E7: =0.632751338890881 -> 0.63275134 | F7: =ROUND(Notes!$B$4*D7+Notes!$B$5*C7+Notes!$B$6*E7,4) -> 0.9452 | G7: =RANK(F7,F$5:F$42,0) -> 3 | H7: =C7 -> 1 | I7: =D7 -> 1 | J7: =E7 -> 0.63275134 | K7: =ROUND(Notes!$B$4*I7+Notes!$B$5*H7+Notes!$B$6*J7,4) -> 0.9452 | L7: =RANK(K7,K$5:K$42,0) -> 3
A8: Lithuania | B8: LTU | C8: =0.826923076923077 -> 0.82692308 | D8: =1 -> 1 | E8: =1 -> 1 | F8: =ROUND(Notes!$B$4*D8+Notes!$B$5*C8+Notes!$B$6*E8,4) -> 0.9288 | G8: =RANK(F8,F$5:F$42,0) -> 4 | H8: =C8 -> 0.82692308 | I8: =D8 -> 1 | J8: =E8 -> 1 | K8: =ROUND(Notes!$B$4*I8+Notes!$B$5*H8+Notes!$B$6*J8,4) -> 0.9288 | L8: =RANK(K8,K$5:K$42,0) -> 4
A9: Canada | B9: CAN | C9: =0.635714285714286 -> 0.63571429 | D9: =1 -> 1 | E9: =0.43 -> 0.43 | F9: =ROUND(Notes!$B$4*D9+Notes!$B$5*C9+Notes!$B$6*E9,4) -> 0.765 | G9: =RANK(F9,F$5:F$42,0) -> 5 | H9: =1 -> 1 | I9: =1 -> 1 | J9: =E9 -> 0.43 | K9: =ROUND(Notes!$B$4*I9+Notes!$B$5*H9+Notes!$B$6*J9,4) -> 0.9149 | L9: =RANK(K9,K$5:K$42,0) -> 5
A10: Italy | B10: ITA | C10: =0.576669379707147 -> 0.57666938 | D10: =0.869865253929667 -> 0.86986525 | E10: =0.965116279069767 -> 0.96511628 | F10: =ROUND(Notes!$B$4*D10+Notes!$B$5*C10+Notes!$B$6*E10,4) -> 0.7634 | G10: =RANK(F10,F$5:F$42,0) -> 6 | H10: =C10 -> 0.57666938 | I10: =D10 -> 0.86986525 | J10: =E10 -> 0.96511628 | K10: =ROUND(Notes!$B$4*I10+Notes!$B$5*H10+Notes!$B$6*J10,4) -> 0.7634 | L10: =RANK(K10,K$5:K$42,0) -> 6
A11: Korea | B11: KOR | C11: =0.547953910556565 -> 0.54795391 | D11: =0.921720532319392 -> 0.92172053 | E11: =0.813463195231154 -> 0.8134632 | F11: =ROUND(Notes!$B$4*D11+Notes!$B$5*C11+Notes!$B$6*E11,4) -> 0.7517 | G11: =RANK(F11,F$5:F$42,0) -> 7 | H11: =C11 -> 0.54795391 | I11: =D11 -> 0.92172053 | J11: =E11 -> 0.8134632 | K11: =ROUND(Notes!$B$4*I11+Notes!$B$5*H11+Notes!$B$6*J11,4) -> 0.7517 | L11: =RANK(K11,K$5:K$42,0) -> 7
A12: Iceland | B12: ISL | C12: =0.602353618717047 -> 0.60235362 | D12: =0.86 -> 0.86 | E12: =0.812269350072009 -> 0.81226935 | F12: =ROUND(Notes!$B$4*D12+Notes!$B$5*C12+Notes!$B$6*E12,4) -> 0.7468 | G12: =RANK(F12,F$5:F$42,0) -> 8 | H12: =C12 -> 0.60235362 | I12: =D12 -> 0.86 | J12: =E12 -> 0.81226935 | K12: =ROUND(Notes!$B$4*I12+Notes!$B$5*H12+Notes!$B$6*J12,4) -> 0.7468 | L12: =RANK(K12,K$5:K$42,0) -> 8
A13: France | B13: FRA | C13: =0.547953910556565 -> 0.54795391 | D13: =0.880275603755891 -> 0.8802756 | E13: =0.869865253929667 -> 0.86986525 | F13: =ROUND(Notes!$B$4*D13+Notes!$B$5*C13+Notes!$B$6*E13,4) -> 0.7419 | G13: =RANK(F13,F$5:F$42,0) -> 9 | H13: =C13 -> 0.54795391 | I13: =D13 -> 0.8802756 | J13: =E13 -> 0.86986525 | K13: =ROUND(Notes!$B$4*I13+Notes!$B$5*H13+Notes!$B$6*J13,4) -> 0.7419 | L13: =RANK(K13,K$5:K$42,0) -> 9
A14: Switzerland | B14: CHE | C14: =0.554838709677419 -> 0.55483871 | D14: =0.86 -> 0.86 | E14: =0.905263157894737 -> 0.90526316 | F14: =ROUND(Notes!$B$4*D14+Notes!$B$5*C14+Notes!$B$6*E14,4) -> 0.7411 | G14: =RANK(F14,F$5:F$42,0) -> 10 | H14: =C14 -> 0.55483871 | I14: =D14 -> 0.86 | J14: =E14 -> 0.90526316 | K14: =ROUND(Notes!$B$4*I14+Notes!$B$5*H14+Notes!$B$6*J14,4) -> 0.7411 | L14: =RANK(K14,K$5:K$42,0) -> 10
A15: Slovakia | B15: SVK | C15: =0.547953910556565 -> 0.54795391 | D15: =0.873879108036537 -> 0.87387911 | E15: =0.869865253929667 -> 0.86986525 | F15: =ROUND(Notes!$B$4*D15+Notes!$B$5*C15+Notes!$B$6*E15,4) -> 0.7391 | G15: =RANK(F15,F$5:F$42,0) -> 11 | H15: =C15 -> 0.54795391 | I15: =D15 -> 0.87387911 | J15: =E15 -> 0.86986525 | K15: =ROUND(Notes!$B$4*I15+Notes!$B$5*H15+Notes!$B$6*J15,4) -> 0.7391 | L15: =RANK(K15,K$5:K$42,0) -> 11
A16: Belgium | B16: BEL | C16: =0.547953910556565 -> 0.54795391 | D16: =0.869865253929667 -> 0.86986525 | E16: =0.869865253929667 -> 0.86986525 | F16: =ROUND(Notes!$B$4*D16+Notes!$B$5*C16+Notes!$B$6*E16,4) -> 0.7373 | G16: =RANK(F16,F$5:F$42,0) -> 12 | H16: =C16 -> 0.54795391 | I16: =D16 -> 0.86986525 | J16: =E16 -> 0.86986525 | K16: =ROUND(Notes!$B$4*I16+Notes!$B$5*H16+Notes!$B$6*J16,4) -> 0.7373 | L16: =RANK(K16,K$5:K$42,0) -> 12
A17: Czech Republic | B17: CZE | C17: =0.543222830616488 -> 0.54322283 | D17: =0.873879108036537 -> 0.87387911 | E17: =0.841318847888109 -> 0.84131885 | F17: =ROUND(Notes!$B$4*D17+Notes!$B$5*C17+Notes!$B$6*E17,4) -> 0.7329 | G17: =RANK(F17,F$5:F$42,0) -> 13 | H17: =C17 -> 0.54322283 | I17: =D17 -> 0.87387911 | J17: =E17 -> 0.84131885 | K17: =ROUND(Notes!$B$4*I17+Notes!$B$5*H17+Notes!$B$6*J17,4) -> 0.7329 | L17: =RANK(K17,K$5:K$42,0) -> 13
A18: Mexico | B18: MEX | C18: =0.630382676079967 -> 0.63038268 | D18: =0.795219524916135 -> 0.79521952 | E18: =0.795219524916135 -> 0.79521952 | F18: =ROUND(Notes!$B$4*D18+Notes!$B$5*C18+Notes!$B$6*E18,4) -> 0.7274 | G18: =RANK(F18,F$5:F$42,0) -> 14 | H18: =C18 -> 0.63038268 | I18: =D18 -> 0.79521952 | J18: =E18 -> 0.79521952 | K18: =ROUND(Notes!$B$4*I18+Notes!$B$5*H18+Notes!$B$6*J18,4) -> 0.7274 | L18: =RANK(K18,K$5:K$42,0) -> 14
A19: United Kingdom | B19: GBR | C19: =0.391406012913837 -> 0.39140601 | D19: =1 -> 1 | E19: =0.826923076923077 -> 0.82692308 | F19: =ROUND(Notes!$B$4*D19+Notes!$B$5*C19+Notes!$B$6*E19,4) -> 0.7236 | G19: =RANK(F19,F$5:F$42,0) -> 15 | H19: =C19 -> 0.39140601 | I19: =D19 -> 1 | J19: =E19 -> 0.82692308 | K19: =ROUND(Notes!$B$4*I19+Notes!$B$5*H19+Notes!$B$6*J19,4) -> 0.7236 | L19: =RANK(K19,K$5:K$42,0) -> 15
A20: Israel | B20: ISR | C20: =0.478865241362287 -> 0.47886524 | D20: =0.901030024355631 -> 0.90103002 | E20: =0.835370889649727 -> 0.83537089 | F20: =ROUND(Notes!$B$4*D20+Notes!$B$5*C20+Notes!$B$6*E20,4) -> 0.7174 | G20: =RANK(F20,F$5:F$42,0) -> 16 | H20: =C20 -> 0.47886524 | I20: =D20 -> 0.90103002 | J20: =E20 -> 0.83537089 | K20: =ROUND(Notes!$B$4*I20+Notes!$B$5*H20+Notes!$B$6*J20,4) -> 0.7174 | L20: =RANK(K20,K$5:K$42,0) -> 16
A21: Luxembourg | B21: LUX | C21: =0.479318672008477 -> 0.47931867 | D21: =0.873417350634541 -> 0.87341735 | E21: =0.869865253929667 -> 0.86986525 | F21: =ROUND(Notes!$B$4*D21+Notes!$B$5*C21+Notes!$B$6*E21,4) -> 0.7107 | G21: =RANK(F21,F$5:F$42,0) -> 17 | H21: =C21 -> 0.47931867 | I21: =D21 -> 0.87341735 | J21: =E21 -> 0.86986525 | K21: =ROUND(Notes!$B$4*I21+Notes!$B$5*H21+Notes!$B$6*J21,4) -> 0.7107 | L21: =RANK(K21,K$5:K$42,0) -> 17
A22: Sweden | B22: SWE | C22: =0.479318672008477 -> 0.47931867 | D22: =0.86 -> 0.86 | E22: =0.86 -> 0.86 | F22: =ROUND(Notes!$B$4*D22+Notes!$B$5*C22+Notes!$B$6*E22,4) -> 0.7033 | G22: =RANK(F22,F$5:F$42,0) -> 18 | H22: =C22 -> 0.47931867 | I22: =D22 -> 0.86 | J22: =E22 -> 0.86 | K22: =ROUND(Notes!$B$4*I22+Notes!$B$5*H22+Notes!$B$6*J22,4) -> 0.7033 | L22: =RANK(K22,K$5:K$42,0) -> 18
A23: Portugal | B23: PRT | C23: =0.547953910556565 -> 0.54795391 | D23: =0.888411247396436 -> 0.88841125 | E23: =0.547953910556565 -> 0.54795391 | F23: =ROUND(Notes!$B$4*D23+Notes!$B$5*C23+Notes!$B$6*E23,4) -> 0.6975 | G23: =RANK(F23,F$5:F$42,0) -> 19 | H23: =C23 -> 0.54795391 | I23: =D23 -> 0.88841125 | J23: =E23 -> 0.54795391 | K23: =ROUND(Notes!$B$4*I23+Notes!$B$5*H23+Notes!$B$6*J23,4) -> 0.6975 | L23: =RANK(K23,K$5:K$42,0) -> 19
A24: Finland | B24: FIN | C24: =0.518965517241379 -> 0.51896552 | D24: =0.826923076923077 -> 0.82692308 | E24: =0.737888702767901 -> 0.7378887 | F24: =ROUND(Notes!$B$4*D24+Notes!$B$5*C24+Notes!$B$6*E24,4) -> 0.6869 | G24: =RANK(F24,F$5:F$42,0) -> 20 | H24: =C24 -> 0.51896552 | I24: =D24 -> 0.82692308 | J24: =E24 -> 0.7378887 | K24: =ROUND(Notes!$B$4*I24+Notes!$B$5*H24+Notes!$B$6*J24,4) -> 0.6869 | L24: =RANK(K24,K$5:K$42,0) -> 20
A25: Germany | B25: DEU | C25: =0.391406012913837 -> 0.39140601 | D25: =0.737888702767901 -> 0.7378887 | E25: =0.869865253929667 -> 0.86986525 | F25: =ROUND(Notes!$B$4*D25+Notes!$B$5*C25+Notes!$B$6*E25,4) -> 0.6149 | G25: =RANK(F25,F$5:F$42,0) -> 29 | H25: =C25 -> 0.39140601 | I25: =D25 -> 0.7378887 | J25: =E25 -> 0.86986525 | K25: =ROUND(Notes!$B$4*I25+Notes!$B$5*H25+Notes!$B$6*J25,4) -> 0.6149 | L25: =RANK(K25,K$5:K$42,0) -> 29
A26: Austria | B26: AUT | C26: =0.408845614108812 -> 0.40884561 | D26: =0.884365027341364 -> 0.88436503 | E26: =0.737888702767901 -> 0.7378887 | F26: =ROUND(Notes!$B$4*D26+Notes!$B$5*C26+Notes!$B$6*E26,4) -> 0.6668 | G26: =RANK(F26,F$5:F$42,0) -> 21 | H26: =C26 -> 0.40884561 | I26: =D26 -> 0.88436503 | J26: =E26 -> 0.7378887 | K26: =ROUND(Notes!$B$4*I26+Notes!$B$5*H26+Notes!$B$6*J26,4) -> 0.6668 | L26: =RANK(K26,K$5:K$42,0) -> 21
A27: Turkey | B27: TUR | C27: =0.431068736527055 -> 0.43106874 | D27: =0.864149148541634 -> 0.86414915 | E27: =0.69441435606903 -> 0.69441436 | F27: =ROUND(Notes!$B$4*D27+Notes!$B$5*C27+Notes!$B$6*E27,4) -> 0.6605 | G27: =RANK(F27,F$5:F$42,0) -> 22 | H27: =C27 -> 0.43106874 | I27: =D27 -> 0.86414915 | J27: =E27 -> 0.69441436 | K27: =ROUND(Notes!$B$4*I27+Notes!$B$5*H27+Notes!$B$6*J27,4) -> 0.6605 | L27: =RANK(K27,K$5:K$42,0) -> 22
A28: Slovenia | B28: SVN | C28: =0.391406012913837 -> 0.39140601 | D28: =0.869865253929667 -> 0.86986525 | E28: =0.737888702767901 -> 0.7378887 | F28: =ROUND(Notes!$B$4*D28+Notes!$B$5*C28+Notes!$B$6*E28,4) -> 0.6532 | G28: =RANK(F28,F$5:F$42,0) -> 23 | H28: =C28 -> 0.39140601 | I28: =D28 -> 0.86986525 | J28: =E28 -> 0.7378887 | K28: =ROUND(Notes!$B$4*I28+Notes!$B$5*H28+Notes!$B$6*J28,4) -> 0.6532 | L28: =RANK(K28,K$5:K$42,0) -> 23
A29: Australia | B29: AUS | C29: =0.479318672008477 -> 0.47931867 | D29: =0.851484971473245 -> 0.85148497 | E29: =0.547953910556565 -> 0.54795391 | F29: =ROUND(Notes!$B$4*D29+Notes!$B$5*C29+Notes!$B$6*E29,4) -> 0.653 | G29: =RANK(F29,F$5:F$42,0) -> 24 | H29: =C29 -> 0.47931867 | I29: =D29 -> 0.85148497 | J29: =E29 -> 0.54795391 | K29: =ROUND(Notes!$B$4*I29+Notes!$B$5*H29+Notes!$B$6*J29,4) -> 0.653 | L29: =RANK(K29,K$5:K$42,0) -> 24
A30: Denmark | B30: DNK | C30: =0.391406012913837 -> 0.39140601 | D30: =0.826923076923077 -> 0.82692308 | E30: =0.81340644290143 -> 0.81340644 | F30: =ROUND(Notes!$B$4*D30+Notes!$B$5*C30+Notes!$B$6*E30,4) -> 0.6456 | G30: =RANK(F30,F$5:F$42,0) -> 25 | H30: =C30 -> 0.39140601 | I30: =D30 -> 0.82692308 | J30: =E30 -> 0.81340644 | K30: =ROUND(Notes!$B$4*I30+Notes!$B$5*H30+Notes!$B$6*J30,4) -> 0.6456 | L30: =RANK(K30,K$5:K$42,0) -> 25
A31: Ireland | B31: IRL | C31: =0.479318672008477 -> 0.47931867 | D31: =0.787075165170195 -> 0.78707517 | E31: =0.646263719038607 -> 0.64626372 | F31: =ROUND(Notes!$B$4*D31+Notes!$B$5*C31+Notes!$B$6*E31,4) -> 0.6394 | G31: =RANK(F31,F$5:F$42,0) -> 26 | H31: =C31 -> 0.47931867 | I31: =D31 -> 0.78707517 | J31: =E31 -> 0.64626372 | K31: =ROUND(Notes!$B$4*I31+Notes!$B$5*H31+Notes!$B$6*J31,4) -> 0.6394 | L31: =RANK(K31,K$5:K$42,0) -> 26
A32: Greece | B32: GRC | C32: =0.479318672008477 -> 0.47931867 | D32: =0.737888702767901 -> 0.7378887 | E32: =0.737888702767901 -> 0.7378887 | F32: =ROUND(Notes!$B$4*D32+Notes!$B$5*C32+Notes!$B$6*E32,4) -> 0.6314 | G32: =RANK(F32,F$5:F$42,0) -> 27 | H32: =C32 -> 0.47931867 | I32: =D32 -> 0.7378887 | J32: =E32 -> 0.7378887 | K32: =ROUND(Notes!$B$4*I32+Notes!$B$5*H32+Notes!$B$6*J32,4) -> 0.6314 | L32: =RANK(K32,K$5:K$42,0) -> 27
A33: Netherlands | B33: NLD | C33: =0.338474732816403 -> 0.33847473 | D33: =0.813463195231154 -> 0.8134632 | E33: =0.869865253929667 -> 0.86986525 | F33: =ROUND(Notes!$B$4*D33+Notes!$B$5*C33+Notes!$B$6*E33,4) -> 0.6263 | G33: =RANK(F33,F$5:F$42,0) -> 28 | H33: =C33 -> 0.33847473 | I33: =D33 -> 0.8134632 | J33: =E33 -> 0.86986525 | K33: =ROUND(Notes!$B$4*I33+Notes!$B$5*H33+Notes!$B$6*J33,4) -> 0.6263 | L33: =RANK(K33,K$5:K$42,0) -> 28
A34: Spain | B34: ESP | C34: =0.391406012913837 -> 0.39140601 | D34: =0.778563038959402 -> 0.77856304 | E34: =0.737888702767901 -> 0.7378887 | F34: =ROUND(Notes!$B$4*D34+Notes!$B$5*C34+Notes!$B$6*E34,4) -> 0.6131 | G34: =RANK(F34,F$5:F$42,0) -> 30 | H34: =C34 -> 0.39140601 | I34: =D34 -> 0.77856304 | J34: =E34 -> 0.7378887 | K34: =ROUND(Notes!$B$4*I34+Notes!$B$5*H34+Notes!$B$6*J34,4) -> 0.6131 | L34: =RANK(K34,K$5:K$42,0) -> 30
A35: Japan | B35: JPN | C35: =0.278958448750364 -> 0.27895845 | D35: =0.859028659709284 -> 0.85902866 | E35: =0.787075165170195 -> 0.78707517 | F35: =ROUND(Notes!$B$4*D35+Notes!$B$5*C35+Notes!$B$6*E35,4) -> 0.6095 | G35: =RANK(F35,F$5:F$42,0) -> 31 | H35: =C35 -> 0.27895845 | I35: =D35 -> 0.85902866 | J35: =E35 -> 0.78707517 | K35: =ROUND(Notes!$B$4*I35+Notes!$B$5*H35+Notes!$B$6*J35,4) -> 0.6095 | L35: =RANK(K35,K$5:K$42,0) -> 31
A36: Norway | B36: NOR | C36: =0.373913043478261 -> 0.37391304 | D36: =0.781818181818182 -> 0.78181818 | E36: =0.737888702767901 -> 0.7378887 | F36: =ROUND(Notes!$B$4*D36+Notes!$B$5*C36+Notes!$B$6*E36,4) -> 0.6073 | G36: =RANK(F36,F$5:F$42,0) -> 32 | H36: =C36 -> 0.37391304 | I36: =D36 -> 0.78181818 | J36: =E36 -> 0.7378887 | K36: =ROUND(Notes!$B$4*I36+Notes!$B$5*H36+Notes!$B$6*J36,4) -> 0.6073 | L36: =RANK(K36,K$5:K$42,0) -> 32
A37: Poland | B37: POL | C37: =0.338474732816403 -> 0.33847473 | D37: =0.737888702767901 -> 0.7378887 | E37: =0.869865253929667 -> 0.86986525 | F37: =ROUND(Notes!$B$4*D37+Notes!$B$5*C37+Notes!$B$6*E37,4) -> 0.5932 | G37: =RANK(F37,F$5:F$42,0) -> 33 | H37: =C37 -> 0.33847473 | I37: =D37 -> 0.7378887 | J37: =E37 -> 0.86986525 | K37: =ROUND(Notes!$B$4*I37+Notes!$B$5*H37+Notes!$B$6*J37,4) -> 0.5932 | L37: =RANK(K37,K$5:K$42,0) -> 33
A38: Costa Rica | B38: CRI | C38: =0.278958448750364 -> 0.27895845 | D38: =0.822456690745778 -> 0.82245669 | E38: =0.737888702767901 -> 0.7378887 | F38: =ROUND(Notes!$B$4*D38+Notes!$B$5*C38+Notes!$B$6*E38,4) -> 0.5861 | G38: =RANK(F38,F$5:F$42,0) -> 34 | H38: =C38 -> 0.27895845 | I38: =D38 -> 0.82245669 | J38: =E38 -> 0.7378887 | K38: =ROUND(Notes!$B$4*I38+Notes!$B$5*H38+Notes!$B$6*J38,4) -> 0.5861 | L38: =RANK(K38,K$5:K$42,0) -> 34
A39: Hungary | B39: HUN | C39: =0.278958448750364 -> 0.27895845 | D39: =0.816200383417959 -> 0.81620038 | E39: =0.737888702767901 -> 0.7378887 | F39: =ROUND(Notes!$B$4*D39+Notes!$B$5*C39+Notes!$B$6*E39,4) -> 0.5834 | G39: =RANK(F39,F$5:F$42,0) -> 35 | H39: =C39 -> 0.27895845 | I39: =D39 -> 0.81620038 | J39: =E39 -> 0.7378887 | K39: =ROUND(Notes!$B$4*I39+Notes!$B$5*H39+Notes!$B$6*J39,4) -> 0.5834 | L39: =RANK(K39,K$5:K$42,0) -> 35
A40: Colombia | B40: COL | C40: =0.305956530933891 -> 0.30595653 | D40: =0.737888702767901 -> 0.7378887 | E40: =0.869865253929667 -> 0.86986525 | F40: =ROUND(Notes!$B$4*D40+Notes!$B$5*C40+Notes!$B$6*E40,4) -> 0.5798 | G40: =RANK(F40,F$5:F$42,0) -> 36 | H40: =C40 -> 0.30595653 | I40: =D40 -> 0.7378887 | J40: =E40 -> 0.86986525 | K40: =ROUND(Notes!$B$4*I40+Notes!$B$5*H40+Notes!$B$6*J40,4) -> 0.5798 | L40: =RANK(K40,K$5:K$42,0) -> 36
A41: New Zealand | B41: NZL | C41: =0.2 -> 0.2 | D41: =0.74468085106383 -> 0.74468085 | E41: =0.547953910556565 -> 0.54795391 | F41: =ROUND(Notes!$B$4*D41+Notes!$B$5*C41+Notes!$B$6*E41,4) -> 0.4911 | G41: =RANK(F41,F$5:F$42,0) -> 37 | H41: =C41 -> 0.2 | I41: =D41 -> 0.74468085 | J41: =E41 -> 0.54795391 | K41: =ROUND(Notes!$B$4*I41+Notes!$B$5*H41+Notes!$B$6*J41,4) -> 0.4911 | L41: =RANK(K41,K$5:K$42,0) -> 37
A42: Chile | B42: CHL | C42: =0.42321653857669 -> 0.42321654 | D42: =0.705977756078566 -> 0.70597776 | E42: =0 -> 0 | F42: =ROUND(Notes!$B$4*D42+Notes!$B$5*C42+Notes!$B$6*E42,4) -> 0.4842 | G42: =RANK(F42,F$5:F$42,0) -> 38 | H42: =C42 -> 0.42321654 | I42: =D42 -> 0.70597776 | J42: =E42 -> 0 | K42: =ROUND(Notes!$B$4*I42+Notes!$B$5*H42+Notes!$B$6*J42,4) -> 0.4842 | L42: =RANK(K42,K$5:K$42,0) -> 38

Sheet 2029
A1: Net Present Value of Capital Allowances, OECD Ranking 2029: current law vs. Canada immediate-expensing reform
A2: Weighted avg = weights (Notes) applied to asset NPVs (source: final-data/npv_all_years.csv). Reform sets Canada machinery and buildings to 1.0; intangibles unchanged. Ranks: RANK on weighted avg rounded to 4 dp, ties=min.
A4: Country | B4: ISO | C4: Buildings (current law) | D4: Machinery (current law) | E4: Intangibles (current law) | F4: Weighted avg (current law) | G4: Rank (current law) | H4: Buildings (reform) | I4: Machinery (reform) | J4: Intangibles (reform) | K4: Weighted avg (reform) | L4: Rank (reform)
A5: Estonia | B5: EST | C5: =1 -> 1 | D5: =1 -> 1 | E5: =1 -> 1 | F5: =ROUND(Notes!$B$4*D5+Notes!$B$5*C5+Notes!$B$6*E5,4) -> 1 | G5: =RANK(F5,F$5:F$42,0) -> 1 | H5: =C5 -> 1 | I5: =D5 -> 1 | J5: =E5 -> 1 | K5: =ROUND(Notes!$B$4*I5+Notes!$B$5*H5+Notes!$B$6*J5,4) -> 1 | L5: =RANK(K5,K$5:K$42,0) -> 1
A6: Latvia | B6: LVA | C6: =1 -> 1 | D6: =1 -> 1 | E6: =1 -> 1 | F6: =ROUND(Notes!$B$4*D6+Notes!$B$5*C6+Notes!$B$6*E6,4) -> 1 | G6: =RANK(F6,F$5:F$42,0) -> 1 | H6: =C6 -> 1 | I6: =D6 -> 1 | J6: =E6 -> 1 | K6: =ROUND(Notes!$B$4*I6+Notes!$B$5*H6+Notes!$B$6*J6,4) -> 1 | L6: =RANK(K6,K$5:K$42,0) -> 1
A7: United States | B7: USA | C7: =0.34958311169213 -> 0.34958311 | D7: =1 -> 1 | E7: =0.632751338890881 -> 0.63275134 | F7: =ROUND(Notes!$B$4*D7+Notes!$B$5*C7+Notes!$B$6*E7,4) -> 0.6774 | G7: =RANK(F7,F$5:F$42,0) -> 20 | H7: =C7 -> 0.34958311 | I7: =D7 -> 1 | J7: =E7 -> 0.63275134 | K7: =ROUND(Notes!$B$4*I7+Notes!$B$5*H7+Notes!$B$6*J7,4) -> 0.6774 | L7: =RANK(K7,K$5:K$42,0) -> 20
A8: Lithuania | B8: LTU | C8: =0.826923076923077 -> 0.82692308 | D8: =1 -> 1 | E8: =1 -> 1 | F8: =ROUND(Notes!$B$4*D8+Notes!$B$5*C8+Notes!$B$6*E8,4) -> 0.9288 | G8: =RANK(F8,F$5:F$42,0) -> 3 | H8: =C8 -> 0.82692308 | I8: =D8 -> 1 | J8: =E8 -> 1 | K8: =ROUND(Notes!$B$4*I8+Notes!$B$5*H8+Notes!$B$6*J8,4) -> 0.9288 | L8: =RANK(K8,K$5:K$42,0) -> 3
A9: Canada | B9: CAN | C9: =0.635714285714286 -> 0.63571429 | D9: =1 -> 1 | E9: =0.43 -> 0.43 | F9: =ROUND(Notes!$B$4*D9+Notes!$B$5*C9+Notes!$B$6*E9,4) -> 0.765 | G9: =RANK(F9,F$5:F$42,0) -> 4 | H9: =1 -> 1 | I9: =1 -> 1 | J9: =E9 -> 0.43 | K9: =ROUND(Notes!$B$4*I9+Notes!$B$5*H9+Notes!$B$6*J9,4) -> 0.9149 | L9: =RANK(K9,K$5:K$42,0) -> 4
A10: Italy | B10: ITA | C10: =0.576669379707147 -> 0.57666938 | D10: =0.869865253929667 -> 0.86986525 | E10: =0.965116279069767 -> 0.96511628 | F10: =ROUND(Notes!$B$4*D10+Notes!$B$5*C10+Notes!$B$6*E10,4) -> 0.7634 | G10: =RANK(F10,F$5:F$42,0) -> 5 | H10: =C10 -> 0.57666938 | I10: =D10 -> 0.86986525 | J10: =E10 -> 0.96511628 | K10: =ROUND(Notes!$B$4*I10+Notes!$B$5*H10+Notes!$B$6*J10,4) -> 0.7634 | L10: =RANK(K10,K$5:K$42,0) -> 5
A11: Korea | B11: KOR | C11: =0.547953910556565 -> 0.54795391 | D11: =0.921720532319392 -> 0.92172053 | E11: =0.813463195231154 -> 0.8134632 | F11: =ROUND(Notes!$B$4*D11+Notes!$B$5*C11+Notes!$B$6*E11,4) -> 0.7517 | G11: =RANK(F11,F$5:F$42,0) -> 6 | H11: =C11 -> 0.54795391 | I11: =D11 -> 0.92172053 | J11: =E11 -> 0.8134632 | K11: =ROUND(Notes!$B$4*I11+Notes!$B$5*H11+Notes!$B$6*J11,4) -> 0.7517 | L11: =RANK(K11,K$5:K$42,0) -> 6
A12: Iceland | B12: ISL | C12: =0.602353618717047 -> 0.60235362 | D12: =0.86 -> 0.86 | E12: =0.812269350072009 -> 0.81226935 | F12: =ROUND(Notes!$B$4*D12+Notes!$B$5*C12+Notes!$B$6*E12,4) -> 0.7468 | G12: =RANK(F12,F$5:F$42,0) -> 7 | H12: =C12 -> 0.60235362 | I12: =D12 -> 0.86 | J12: =E12 -> 0.81226935 | K12: =ROUND(Notes!$B$4*I12+Notes!$B$5*H12+Notes!$B$6*J12,4) -> 0.7468 | L12: =RANK(K12,K$5:K$42,0) -> 7
A13: France | B13: FRA | C13: =0.547953910556565 -> 0.54795391 | D13: =0.880275603755891 -> 0.8802756 | E13: =0.869865253929667 -> 0.86986525 | F13: =ROUND(Notes!$B$4*D13+Notes!$B$5*C13+Notes!$B$6*E13,4) -> 0.7419 | G13: =RANK(F13,F$5:F$42,0) -> 8 | H13: =C13 -> 0.54795391 | I13: =D13 -> 0.8802756 | J13: =E13 -> 0.86986525 | K13: =ROUND(Notes!$B$4*I13+Notes!$B$5*H13+Notes!$B$6*J13,4) -> 0.7419 | L13: =RANK(K13,K$5:K$42,0) -> 8
A14: Switzerland | B14: CHE | C14: =0.554838709677419 -> 0.55483871 | D14: =0.86 -> 0.86 | E14: =0.905263157894737 -> 0.90526316 | F14: =ROUND(Notes!$B$4*D14+Notes!$B$5*C14+Notes!$B$6*E14,4) -> 0.7411 | G14: =RANK(F14,F$5:F$42,0) -> 9 | H14: =C14 -> 0.55483871 | I14: =D14 -> 0.86 | J14: =E14 -> 0.90526316 | K14: =ROUND(Notes!$B$4*I14+Notes!$B$5*H14+Notes!$B$6*J14,4) -> 0.7411 | L14: =RANK(K14,K$5:K$42,0) -> 9
A15: Slovakia | B15: SVK | C15: =0.547953910556565 -> 0.54795391 | D15: =0.873879108036537 -> 0.87387911 | E15: =0.869865253929667 -> 0.86986525 | F15: =ROUND(Notes!$B$4*D15+Notes!$B$5*C15+Notes!$B$6*E15,4) -> 0.7391 | G15: =RANK(F15,F$5:F$42,0) -> 10 | H15: =C15 -> 0.54795391 | I15: =D15 -> 0.87387911 | J15: =E15 -> 0.86986525 | K15: =ROUND(Notes!$B$4*I15+Notes!$B$5*H15+Notes!$B$6*J15,4) -> 0.7391 | L15: =RANK(K15,K$5:K$42,0) -> 10
A16: Belgium | B16: BEL | C16: =0.547953910556565 -> 0.54795391 | D16: =0.869865253929667 -> 0.86986525 | E16: =0.869865253929667 -> 0.86986525 | F16: =ROUND(Notes!$B$4*D16+Notes!$B$5*C16+Notes!$B$6*E16,4) -> 0.7373 | G16: =RANK(F16,F$5:F$42,0) -> 11 | H16: =C16 -> 0.54795391 | I16: =D16 -> 0.86986525 | J16: =E16 -> 0.86986525 | K16: =ROUND(Notes!$B$4*I16+Notes!$B$5*H16+Notes!$B$6*J16,4) -> 0.7373 | L16: =RANK(K16,K$5:K$42,0) -> 11
A17: Czech Republic | B17: CZE | C17: =0.543222830616488 -> 0.54322283 | D17: =0.873879108036537 -> 0.87387911 | E17: =0.841318847888109 -> 0.84131885 | F17: =ROUND(Notes!$B$4*D17+Notes!$B$5*C17+Notes!$B$6*E17,4) -> 0.7329 | G17: =RANK(F17,F$5:F$42,0) -> 12 | H17: =C17 -> 0.54322283 | I17: =D17 -> 0.87387911 | J17: =E17 -> 0.84131885 | K17: =ROUND(Notes!$B$4*I17+Notes!$B$5*H17+Notes!$B$6*J17,4) -> 0.7329 | L17: =RANK(K17,K$5:K$42,0) -> 12
A18: Mexico | B18: MEX | C18: =0.630382676079967 -> 0.63038268 | D18: =0.795219524916135 -> 0.79521952 | E18: =0.795219524916135 -> 0.79521952 | F18: =ROUND(Notes!$B$4*D18+Notes!$B$5*C18+Notes!$B$6*E18,4) -> 0.7274 | G18: =RANK(F18,F$5:F$42,0) -> 13 | H18: =C18 -> 0.63038268 | I18: =D18 -> 0.79521952 | J18: =E18 -> 0.79521952 | K18: =ROUND(Notes!$B$4*I18+Notes!$B$5*H18+Notes!$B$6*J18,4) -> 0.7274 | L18: =RANK(K18,K$5:K$42,0) -> 13
A19: United Kingdom | B19: GBR | C19: =0.391406012913837 -> 0.39140601 | D19: =1 -> 1 | E19: =0.826923076923077 -> 0.82692308 | F19: =ROUND(Notes!$B$4*D19+Notes!$B$5*C19+Notes!$B$6*E19,4) -> 0.7236 | G19: =RANK(F19,F$5:F$42,0) -> 14 | H19: =C19 -> 0.39140601 | I19: =D19 -> 1 | J19: =E19 -> 0.82692308 | K19: =ROUND(Notes!$B$4*I19+Notes!$B$5*H19+Notes!$B$6*J19,4) -> 0.7236 | L19: =RANK(K19,K$5:K$42,0) -> 14
A20: Israel | B20: ISR | C20: =0.478865241362287 -> 0.47886524 | D20: =0.901030024355631 -> 0.90103002 | E20: =0.835370889649727 -> 0.83537089 | F20: =ROUND(Notes!$B$4*D20+Notes!$B$5*C20+Notes!$B$6*E20,4) -> 0.7174 | G20: =RANK(F20,F$5:F$42,0) -> 15 | H20: =C20 -> 0.47886524 | I20: =D20 -> 0.90103002 | J20: =E20 -> 0.83537089 | K20: =ROUND(Notes!$B$4*I20+Notes!$B$5*H20+Notes!$B$6*J20,4) -> 0.7174 | L20: =RANK(K20,K$5:K$42,0) -> 15
A21: Luxembourg | B21: LUX | C21: =0.479318672008477 -> 0.47931867 | D21: =0.873417350634541 -> 0.87341735 | E21: =0.869865253929667 -> 0.86986525 | F21: =ROUND(Notes!$B$4*D21+Notes!$B$5*C21+Notes!$B$6*E21,4) -> 0.7107 | G21: =RANK(F21,F$5:F$42,0) -> 16 | H21: =C21 -> 0.47931867 | I21: =D21 -> 0.87341735 | J21: =E21 -> 0.86986525 | K21: =ROUND(Notes!$B$4*I21+Notes!$B$5*H21+Notes!$B$6*J21,4) -> 0.7107 | L21: =RANK(K21,K$5:K$42,0) -> 16
A22: Sweden | B22: SWE | C22: =0.479318672008477 -> 0.47931867 | D22: =0.86 -> 0.86 | E22: =0.86 -> 0.86 | F22: =ROUND(Notes!$B$4*D22+Notes!$B$5*C22+Notes!$B$6*E22,4) -> 0.7033 | G22: =RANK(F22,F$5:F$42,0) -> 17 | H22: =C22 -> 0.47931867 | I22: =D22 -> 0.86 | J22: =E22 -> 0.86 | K22: =ROUND(Notes!$B$4*I22+Notes!$B$5*H22+Notes!$B$6*J22,4) -> 0.7033 | L22: =RANK(K22,K$5:K$42,0) -> 17
A23: Portugal | B23: PRT | C23: =0.547953910556565 -> 0.54795391 | D23: =0.888411247396436 -> 0.88841125 | E23: =0.547953910556565 -> 0.54795391 | F23: =ROUND(Notes!$B$4*D23+Notes!$B$5*C23+Notes!$B$6*E23,4) -> 0.6975 | G23: =RANK(F23,F$5:F$42,0) -> 18 | H23: =C23 -> 0.54795391 | I23: =D23 -> 0.88841125 | J23: =E23 -> 0.54795391 | K23: =ROUND(Notes!$B$4*I23+Notes!$B$5*H23+Notes!$B$6*J23,4) -> 0.6975 | L23: =RANK(K23,K$5:K$42,0) -> 18
A24: Finland | B24: FIN | C24: =0.518965517241379 -> 0.51896552 | D24: =0.826923076923077 -> 0.82692308 | E24: =0.737888702767901 -> 0.7378887 | F24: =ROUND(Notes!$B$4*D24+Notes!$B$5*C24+Notes!$B$6*E24,4) -> 0.6869 | G24: =RANK(F24,F$5:F$42,0) -> 19 | H24: =C24 -> 0.51896552 | I24: =D24 -> 0.82692308 | J24: =E24 -> 0.7378887 | K24: =ROUND(Notes!$B$4*I24+Notes!$B$5*H24+Notes!$B$6*J24,4) -> 0.6869 | L24: =RANK(K24,K$5:K$42,0) -> 19
A25: Germany | B25: DEU | C25: =0.391406012913837 -> 0.39140601 | D25: =0.737888702767901 -> 0.7378887 | E25: =0.869865253929667 -> 0.86986525 | F25: =ROUND(Notes!$B$4*D25+Notes!$B$5*C25+Notes!$B$6*E25,4) -> 0.6149 | G25: =RANK(F25,F$5:F$42,0) -> 29 | H25: =C25 -> 0.39140601 | I25: =D25 -> 0.7378887 | J25: =E25 -> 0.86986525 | K25: =ROUND(Notes!$B$4*I25+Notes!$B$5*H25+Notes!$B$6*J25,4) -> 0.6149 | L25: =RANK(K25,K$5:K$42,0) -> 29
A26: Austria | B26: AUT | C26: =0.408845614108812 -> 0.40884561 | D26: =0.884365027341364 -> 0.88436503 | E26: =0.737888702767901 -> 0.7378887 | F26: =ROUND(Notes!$B$4*D26+Notes!$B$5*C26+Notes!$B$6*E26,4) -> 0.6668 | G26: =RANK(F26,F$5:F$42,0) -> 21 | H26: =C26 -> 0.40884561 | I26: =D26 -> 0.88436503 | J26: =E26 -> 0.7378887 | K26: =ROUND(Notes!$B$4*I26+Notes!$B$5*H26+Notes!$B$6*J26,4) -> 0.6668 | L26: =RANK(K26,K$5:K$42,0) -> 21
A27: Turkey | B27: TUR | C27: =0.431068736527055 -> 0.43106874 | D27: =0.864149148541634 -> 0.86414915 | E27: =0.69441435606903 -> 0.69441436 | F27: =ROUND(Notes!$B$4*D27+Notes!$B$5*C27+Notes!$B$6*E27,4) -> 0.6605 | G27: =RANK(F27,F$5:F$42,0) -> 22 | H27: =C27 -> 0.43106874 | I27: =D27 -> 0.86414915 | J27: =E27 -> 0.69441436 | K27: =ROUND(Notes!$B$4*I27+Notes!$B$5*H27+Notes!$B$6*J27,4) -> 0.6605 | L27: =RANK(K27,K$5:K$42,0) -> 22
A28: Slovenia | B28: SVN | C28: =0.391406012913837 -> 0.39140601 | D28: =0.869865253929667 -> 0.86986525 | E28: =0.737888702767901 -> 0.7378887 | F28: =ROUND(Notes!$B$4*D28+Notes!$B$5*C28+Notes!$B$6*E28,4) -> 0.6532 | G28: =RANK(F28,F$5:F$42,0) -> 23 | H28: =C28 -> 0.39140601 | I28: =D28 -> 0.86986525 | J28: =E28 -> 0.7378887 | K28: =ROUND(Notes!$B$4*I28+Notes!$B$5*H28+Notes!$B$6*J28,4) -> 0.6532 | L28: =RANK(K28,K$5:K$42,0) -> 23
A29: Australia | B29: AUS | C29: =0.479318672008477 -> 0.47931867 | D29: =0.851484971473245 -> 0.85148497 | E29: =0.547953910556565 -> 0.54795391 | F29: =ROUND(Notes!$B$4*D29+Notes!$B$5*C29+Notes!$B$6*E29,4) -> 0.653 | G29: =RANK(F29,F$5:F$42,0) -> 24 | H29: =C29 -> 0.47931867 | I29: =D29 -> 0.85148497 | J29: =E29 -> 0.54795391 | K29: =ROUND(Notes!$B$4*I29+Notes!$B$5*H29+Notes!$B$6*J29,4) -> 0.653 | L29: =RANK(K29,K$5:K$42,0) -> 24
A30: Denmark | B30: DNK | C30: =0.391406012913837 -> 0.39140601 | D30: =0.826923076923077 -> 0.82692308 | E30: =0.81340644290143 -> 0.81340644 | F30: =ROUND(Notes!$B$4*D30+Notes!$B$5*C30+Notes!$B$6*E30,4) -> 0.6456 | G30: =RANK(F30,F$5:F$42,0) -> 25 | H30: =C30 -> 0.39140601 | I30: =D30 -> 0.82692308 | J30: =E30 -> 0.81340644 | K30: =ROUND(Notes!$B$4*I30+Notes!$B$5*H30+Notes!$B$6*J30,4) -> 0.6456 | L30: =RANK(K30,K$5:K$42,0) -> 25
A31: Ireland | B31: IRL | C31: =0.479318672008477 -> 0.47931867 | D31: =0.787075165170195 -> 0.78707517 | E31: =0.646263719038607 -> 0.64626372 | F31: =ROUND(Notes!$B$4*D31+Notes!$B$5*C31+Notes!$B$6*E31,4) -> 0.6394 | G31: =RANK(F31,F$5:F$42,0) -> 26 | H31: =C31 -> 0.47931867 | I31: =D31 -> 0.78707517 | J31: =E31 -> 0.64626372 | K31: =ROUND(Notes!$B$4*I31+Notes!$B$5*H31+Notes!$B$6*J31,4) -> 0.6394 | L31: =RANK(K31,K$5:K$42,0) -> 26
A32: Greece | B32: GRC | C32: =0.479318672008477 -> 0.47931867 | D32: =0.737888702767901 -> 0.7378887 | E32: =0.737888702767901 -> 0.7378887 | F32: =ROUND(Notes!$B$4*D32+Notes!$B$5*C32+Notes!$B$6*E32,4) -> 0.6314 | G32: =RANK(F32,F$5:F$42,0) -> 27 | H32: =C32 -> 0.47931867 | I32: =D32 -> 0.7378887 | J32: =E32 -> 0.7378887 | K32: =ROUND(Notes!$B$4*I32+Notes!$B$5*H32+Notes!$B$6*J32,4) -> 0.6314 | L32: =RANK(K32,K$5:K$42,0) -> 27
A33: Netherlands | B33: NLD | C33: =0.338474732816403 -> 0.33847473 | D33: =0.813463195231154 -> 0.8134632 | E33: =0.869865253929667 -> 0.86986525 | F33: =ROUND(Notes!$B$4*D33+Notes!$B$5*C33+Notes!$B$6*E33,4) -> 0.6263 | G33: =RANK(F33,F$5:F$42,0) -> 28 | H33: =C33 -> 0.33847473 | I33: =D33 -> 0.8134632 | J33: =E33 -> 0.86986525 | K33: =ROUND(Notes!$B$4*I33+Notes!$B$5*H33+Notes!$B$6*J33,4) -> 0.6263 | L33: =RANK(K33,K$5:K$42,0) -> 28
A34: Spain | B34: ESP | C34: =0.391406012913837 -> 0.39140601 | D34: =0.778563038959402 -> 0.77856304 | E34: =0.737888702767901 -> 0.7378887 | F34: =ROUND(Notes!$B$4*D34+Notes!$B$5*C34+Notes!$B$6*E34,4) -> 0.6131 | G34: =RANK(F34,F$5:F$42,0) -> 30 | H34: =C34 -> 0.39140601 | I34: =D34 -> 0.77856304 | J34: =E34 -> 0.7378887 | K34: =ROUND(Notes!$B$4*I34+Notes!$B$5*H34+Notes!$B$6*J34,4) -> 0.6131 | L34: =RANK(K34,K$5:K$42,0) -> 30
A35: Japan | B35: JPN | C35: =0.278958448750364 -> 0.27895845 | D35: =0.859028659709284 -> 0.85902866 | E35: =0.787075165170195 -> 0.78707517 | F35: =ROUND(Notes!$B$4*D35+Notes!$B$5*C35+Notes!$B$6*E35,4) -> 0.6095 | G35: =RANK(F35,F$5:F$42,0) -> 31 | H35: =C35 -> 0.27895845 | I35: =D35 -> 0.85902866 | J35: =E35 -> 0.78707517 | K35: =ROUND(Notes!$B$4*I35+Notes!$B$5*H35+Notes!$B$6*J35,4) -> 0.6095 | L35: =RANK(K35,K$5:K$42,0) -> 31
A36: Norway | B36: NOR | C36: =0.373913043478261 -> 0.37391304 | D36: =0.781818181818182 -> 0.78181818 | E36: =0.737888702767901 -> 0.7378887 | F36: =ROUND(Notes!$B$4*D36+Notes!$B$5*C36+Notes!$B$6*E36,4) -> 0.6073 | G36: =RANK(F36,F$5:F$42,0) -> 32 | H36: =C36 -> 0.37391304 | I36: =D36 -> 0.78181818 | J36: =E36 -> 0.7378887 | K36: =ROUND(Notes!$B$4*I36+Notes!$B$5*H36+Notes!$B$6*J36,4) -> 0.6073 | L36: =RANK(K36,K$5:K$42,0) -> 32
A37: Poland | B37: POL | C37: =0.338474732816403 -> 0.33847473 | D37: =0.737888702767901 -> 0.7378887 | E37: =0.869865253929667 -> 0.86986525 | F37: =ROUND(Notes!$B$4*D37+Notes!$B$5*C37+Notes!$B$6*E37,4) -> 0.5932 | G37: =RANK(F37,F$5:F$42,0) -> 33 | H37: =C37 -> 0.33847473 | I37: =D37 -> 0.7378887 | J37: =E37 -> 0.86986525 | K37: =ROUND(Notes!$B$4*I37+Notes!$B$5*H37+Notes!$B$6*J37,4) -> 0.5932 | L37: =RANK(K37,K$5:K$42,0) -> 33
A38: Costa Rica | B38: CRI | C38: =0.278958448750364 -> 0.27895845 | D38: =0.822456690745778 -> 0.82245669 | E38: =0.737888702767901 -> 0.7378887 | F38: =ROUND(Notes!$B$4*D38+Notes!$B$5*C38+Notes!$B$6*E38,4) -> 0.5861 | G38: =RANK(F38,F$5:F$42,0) -> 34 | H38: =C38 -> 0.27895845 | I38: =D38 -> 0.82245669 | J38: =E38 -> 0.7378887 | K38: =ROUND(Notes!$B$4*I38+Notes!$B$5*H38+Notes!$B$6*J38,4) -> 0.5861 | L38: =RANK(K38,K$5:K$42,0) -> 34
A39: Hungary | B39: HUN | C39: =0.278958448750364 -> 0.27895845 | D39: =0.816200383417959 -> 0.81620038 | E39: =0.737888702767901 -> 0.7378887 | F39: =ROUND(Notes!$B$4*D39+Notes!$B$5*C39+Notes!$B$6*E39,4) -> 0.5834 | G39: =RANK(F39,F$5:F$42,0) -> 35 | H39: =C39 -> 0.27895845 | I39: =D39 -> 0.81620038 | J39: =E39 -> 0.7378887 | K39: =ROUND(Notes!$B$4*I39+Notes!$B$5*H39+Notes!$B$6*J39,4) -> 0.5834 | L39: =RANK(K39,K$5:K$42,0) -> 35
A40: Colombia | B40: COL | C40: =0.305956530933891 -> 0.30595653 | D40: =0.737888702767901 -> 0.7378887 | E40: =0.869865253929667 -> 0.86986525 | F40: =ROUND(Notes!$B$4*D40+Notes!$B$5*C40+Notes!$B$6*E40,4) -> 0.5798 | G40: =RANK(F40,F$5:F$42,0) -> 36 | H40: =C40 -> 0.30595653 | I40: =D40 -> 0.7378887 | J40: =E40 -> 0.86986525 | K40: =ROUND(Notes!$B$4*I40+Notes!$B$5*H40+Notes!$B$6*J40,4) -> 0.5798 | L40: =RANK(K40,K$5:K$42,0) -> 36
A41: New Zealand | B41: NZL | C41: =0.2 -> 0.2 | D41: =0.74468085106383 -> 0.74468085 | E41: =0.547953910556565 -> 0.54795391 | F41: =ROUND(Notes!$B$4*D41+Notes!$B$5*C41+Notes!$B$6*E41,4) -> 0.4911 | G41: =RANK(F41,F$5:F$42,0) -> 37 | H41: =C41 -> 0.2 | I41: =D41 -> 0.74468085 | J41: =E41 -> 0.54795391 | K41: =ROUND(Notes!$B$4*I41+Notes!$B$5*H41+Notes!$B$6*J41,4) -> 0.4911 | L41: =RANK(K41,K$5:K$42,0) -> 37
A42: Chile | B42: CHL | C42: =0.42321653857669 -> 0.42321654 | D42: =0.705977756078566 -> 0.70597776 | E42: =0 -> 0 | F42: =ROUND(Notes!$B$4*D42+Notes!$B$5*C42+Notes!$B$6*E42,4) -> 0.4842 | G42: =RANK(F42,F$5:F$42,0) -> 38 | H42: =C42 -> 0.42321654 | I42: =D42 -> 0.70597776 | J42: =E42 -> 0 | K42: =ROUND(Notes!$B$4*I42+Notes!$B$5*H42+Notes!$B$6*J42,4) -> 0.4842 | L42: =RANK(K42,K$5:K$42,0) -> 38

Sheet 2030
A1: Net Present Value of Capital Allowances, OECD Ranking 2030: current law vs. Canada immediate-expensing reform
A2: Weighted avg = weights (Notes) applied to asset NPVs (source: final-data/npv_all_years.csv). Reform sets Canada machinery and buildings to 1.0; intangibles unchanged. Ranks: RANK on weighted avg rounded to 4 dp, ties=min.
A4: Country | B4: ISO | C4: Buildings (current law) | D4: Machinery (current law) | E4: Intangibles (current law) | F4: Weighted avg (current law) | G4: Rank (current law) | H4: Buildings (reform) | I4: Machinery (reform) | J4: Intangibles (reform) | K4: Weighted avg (reform) | L4: Rank (reform)
A5: Estonia | B5: EST | C5: =1 -> 1 | D5: =1 -> 1 | E5: =1 -> 1 | F5: =ROUND(Notes!$B$4*D5+Notes!$B$5*C5+Notes!$B$6*E5,4) -> 1 | G5: =RANK(F5,F$5:F$42,0) -> 1 | H5: =C5 -> 1 | I5: =D5 -> 1 | J5: =E5 -> 1 | K5: =ROUND(Notes!$B$4*I5+Notes!$B$5*H5+Notes!$B$6*J5,4) -> 1 | L5: =RANK(K5,K$5:K$42,0) -> 1
A6: Latvia | B6: LVA | C6: =1 -> 1 | D6: =1 -> 1 | E6: =1 -> 1 | F6: =ROUND(Notes!$B$4*D6+Notes!$B$5*C6+Notes!$B$6*E6,4) -> 1 | G6: =RANK(F6,F$5:F$42,0) -> 1 | H6: =C6 -> 1 | I6: =D6 -> 1 | J6: =E6 -> 1 | K6: =ROUND(Notes!$B$4*I6+Notes!$B$5*H6+Notes!$B$6*J6,4) -> 1 | L6: =RANK(K6,K$5:K$42,0) -> 1
A7: United States | B7: USA | C7: =0.34958311169213 -> 0.34958311 | D7: =1 -> 1 | E7: =0.632751338890881 -> 0.63275134 | F7: =ROUND(Notes!$B$4*D7+Notes!$B$5*C7+Notes!$B$6*E7,4) -> 0.6774 | G7: =RANK(F7,F$5:F$42,0) -> 20 | H7: =C7 -> 0.34958311 | I7: =D7 -> 1 | J7: =E7 -> 0.63275134 | K7: =ROUND(Notes!$B$4*I7+Notes!$B$5*H7+Notes!$B$6*J7,4) -> 0.6774 | L7: =RANK(K7,K$5:K$42,0) -> 20
A8: Lithuania | B8: LTU | C8: =0.826923076923077 -> 0.82692308 | D8: =1 -> 1 | E8: =1 -> 1 | F8: =ROUND(Notes!$B$4*D8+Notes!$B$5*C8+Notes!$B$6*E8,4) -> 0.9288 | G8: =RANK(F8,F$5:F$42,0) -> 3 | H8: =C8 -> 0.82692308 | I8: =D8 -> 1 | J8: =E8 -> 1 | K8: =ROUND(Notes!$B$4*I8+Notes!$B$5*H8+Notes!$B$6*J8,4) -> 0.9288 | L8: =RANK(K8,K$5:K$42,0) -> 3
A9: Canada | B9: CAN | C9: =0.625 -> 0.625 | D9: =0.967391304347826 -> 0.9673913 | E9: =0.43 -> 0.43 | F9: =ROUND(Notes!$B$4*D9+Notes!$B$5*C9+Notes!$B$6*E9,4) -> 0.7462 | G9: =RANK(F9,F$5:F$42,0) -> 7 | H9: =1 -> 1 | I9: =1 -> 1 | J9: =E9 -> 0.43 | K9: =ROUND(Notes!$B$4*I9+Notes!$B$5*H9+Notes!$B$6*J9,4) -> 0.9149 | L9: =RANK(K9,K$5:K$42,0) -> 4
A10: Italy | B10: ITA | C10: =0.576669379707147 -> 0.57666938 | D10: =0.869865253929667 -> 0.86986525 | E10: =0.965116279069767 -> 0.96511628 | F10: =ROUND(Notes!$B$4*D10+Notes!$B$5*C10+Notes!$B$6*E10,4) -> 0.7634 | G10: =RANK(F10,F$5:F$42,0) -> 4 | H10: =C10 -> 0.57666938 | I10: =D10 -> 0.86986525 | J10: =E10 -> 0.96511628 | K10: =ROUND(Notes!$B$4*I10+Notes!$B$5*H10+Notes!$B$6*J10,4) -> 0.7634 | L10: =RANK(K10,K$5:K$42,0) -> 5
A11: Korea | B11: KOR | C11: =0.547953910556565 -> 0.54795391 | D11: =0.921720532319392 -> 0.92172053 | E11: =0.813463195231154 -> 0.8134632 | F11: =ROUND(Notes!$B$4*D11+Notes!$B$5*C11+Notes!$B$6*E11,4) -> 0.7517 | G11: =RANK(F11,F$5:F$42,0) -> 5 | H11: =C11 -> 0.54795391 | I11: =D11 -> 0.92172053 | J11: =E11 -> 0.8134632 | K11: =ROUND(Notes!$B$4*I11+Notes!$B$5*H11+Notes!$B$6*J11,4) -> 0.7517 | L11: =RANK(K11,K$5:K$42,0) -> 6
A12: Iceland | B12: ISL | C12: =0.602353618717047 -> 0.60235362 | D12: =0.86 -> 0.86 | E12: =0.812269350072009 -> 0.81226935 | F12: =ROUND(Notes!$B$4*D12+Notes!$B$5*C12+Notes!$B$6*E12,4) -> 0.7468 | G12: =RANK(F12,F$5:F$42,0) -> 6 | H12: =C12 -> 0.60235362 | I12: =D12 -> 0.86 | J12: =E12 -> 0.81226935 | K12: =ROUND(Notes!$B$4*I12+Notes!$B$5*H12+Notes!$B$6*J12,4) -> 0.7468 | L12: =RANK(K12,K$5:K$42,0) -> 7
A13: France | B13: FRA | C13: =0.547953910556565 -> 0.54795391 | D13: =0.880275603755891 -> 0.8802756 | E13: =0.869865253929667 -> 0.86986525 | F13: =ROUND(Notes!$B$4*D13+Notes!$B$5*C13+Notes!$B$6*E13,4) -> 0.7419 | G13: =RANK(F13,F$5:F$42,0) -> 8 | H13: =C13 -> 0.54795391 | I13: =D13 -> 0.8802756 | J13: =E13 -> 0.86986525 | K13: =ROUND(Notes!$B$4*I13+Notes!$B$5*H13+Notes!$B$6*J13,4) -> 0.7419 | L13: =RANK(K13,K$5:K$42,0) -> 8
A14: Switzerland | B14: CHE | C14: =0.554838709677419 -> 0.55483871 | D14: =0.86 -> 0.86 | E14: =0.905263157894737 -> 0.90526316 | F14: =ROUND(Notes!$B$4*D14+Notes!$B$5*C14+Notes!$B$6*E14,4) -> 0.7411 | G14: =RANK(F14,F$5:F$42,0) -> 9 | H14: =C14 -> 0.55483871 | I14: =D14 -> 0.86 | J14: =E14 -> 0.90526316 | K14: =ROUND(Notes!$B$4*I14+Notes!$B$5*H14+Notes!$B$6*J14,4) -> 0.7411 | L14: =RANK(K14,K$5:K$42,0) -> 9
A15: Slovakia | B15: SVK | C15: =0.547953910556565 -> 0.54795391 | D15: =0.873879108036537 -> 0.87387911 | E15: =0.869865253929667 -> 0.86986525 | F15: =ROUND(Notes!$B$4*D15+Notes!$B$5*C15+Notes!$B$6*E15,4) -> 0.7391 | G15: =RANK(F15,F$5:F$42,0) -> 10 | H15: =C15 -> 0.54795391 | I15: =D15 -> 0.87387911 | J15: =E15 -> 0.86986525 | K15: =ROUND(Notes!$B$4*I15+Notes!$B$5*H15+Notes!$B$6*J15,4) -> 0.7391 | L15: =RANK(K15,K$5:K$42,0) -> 10
A16: Belgium | B16: BEL | C16: =0.547953910556565 -> 0.54795391 | D16: =0.869865253929667 -> 0.86986525 | E16: =0.869865253929667 -> 0.86986525 | F16: =ROUND(Notes!$B$4*D16+Notes!$B$5*C16+Notes!$B$6*E16,4) -> 0.7373 | G16: =RANK(F16,F$5:F$42,0) -> 11 | H16: =C16 -> 0.54795391 | I16: =D16 -> 0.86986525 | J16: =E16 -> 0.86986525 | K16: =ROUND(Notes!$B$4*I16+Notes!$B$5*H16+Notes!$B$6*J16,4) -> 0.7373 | L16: =RANK(K16,K$5:K$42,0) -> 11
A17: Czech Republic | B17: CZE | C17: =0.543222830616488 -> 0.54322283 | D17: =0.873879108036537 -> 0.87387911 | E17: =0.841318847888109 -> 0.84131885 | F17: =ROUND(Notes!$B$4*D17+Notes!$B$5*C17+Notes!$B$6*E17,4) -> 0.7329 | G17: =RANK(F17,F$5:F$42,0) -> 12 | H17: =C17 -> 0.54322283 | I17: =D17 -> 0.87387911 | J17: =E17 -> 0.84131885 | K17: =ROUND(Notes!$B$4*I17+Notes!$B$5*H17+Notes!$B$6*J17,4) -> 0.7329 | L17: =RANK(K17,K$5:K$42,0) -> 12
A18: Mexico | B18: MEX | C18: =0.630382676079967 -> 0.63038268 | D18: =0.795219524916135 -> 0.79521952 | E18: =0.795219524916135 -> 0.79521952 | F18: =ROUND(Notes!$B$4*D18+Notes!$B$5*C18+Notes!$B$6*E18,4) -> 0.7274 | G18: =RANK(F18,F$5:F$42,0) -> 13 | H18: =C18 -> 0.63038268 | I18: =D18 -> 0.79521952 | J18: =E18 -> 0.79521952 | K18: =ROUND(Notes!$B$4*I18+Notes!$B$5*H18+Notes!$B$6*J18,4) -> 0.7274 | L18: =RANK(K18,K$5:K$42,0) -> 13
A19: United Kingdom | B19: GBR | C19: =0.391406012913837 -> 0.39140601 | D19: =1 -> 1 | E19: =0.826923076923077 -> 0.82692308 | F19: =ROUND(Notes!$B$4*D19+Notes!$B$5*C19+Notes!$B$6*E19,4) -> 0.7236 | G19: =RANK(F19,F$5:F$42,0) -> 14 | H19: =C19 -> 0.39140601 | I19: =D19 -> 1 | J19: =E19 -> 0.82692308 | K19: =ROUND(Notes!$B$4*I19+Notes!$B$5*H19+Notes!$B$6*J19,4) -> 0.7236 | L19: =RANK(K19,K$5:K$42,0) -> 14
A20: Israel | B20: ISR | C20: =0.478865241362287 -> 0.47886524 | D20: =0.901030024355631 -> 0.90103002 | E20: =0.835370889649727 -> 0.83537089 | F20: =ROUND(Notes!$B$4*D20+Notes!$B$5*C20+Notes!$B$6*E20,4) -> 0.7174 | G20: =RANK(F20,F$5:F$42,0) -> 15 | H20: =C20 -> 0.47886524 | I20: =D20 -> 0.90103002 | J20: =E20 -> 0.83537089 | K20: =ROUND(Notes!$B$4*I20+Notes!$B$5*H20+Notes!$B$6*J20,4) -> 0.7174 | L20: =RANK(K20,K$5:K$42,0) -> 15
A21: Luxembourg | B21: LUX | C21: =0.479318672008477 -> 0.47931867 | D21: =0.873417350634541 -> 0.87341735 | E21: =0.869865253929667 -> 0.86986525 | F21: =ROUND(Notes!$B$4*D21+Notes!$B$5*C21+Notes!$B$6*E21,4) -> 0.7107 | G21: =RANK(F21,F$5:F$42,0) -> 16 | H21: =C21 -> 0.47931867 | I21: =D21 -> 0.87341735 | J21: =E21 -> 0.86986525 | K21: =ROUND(Notes!$B$4*I21+Notes!$B$5*H21+Notes!$B$6*J21,4) -> 0.7107 | L21: =RANK(K21,K$5:K$42,0) -> 16
A22: Sweden | B22: SWE | C22: =0.479318672008477 -> 0.47931867 | D22: =0.86 -> 0.86 | E22: =0.86 -> 0.86 | F22: =ROUND(Notes!$B$4*D22+Notes!$B$5*C22+Notes!$B$6*E22,4) -> 0.7033 | G22: =RANK(F22,F$5:F$42,0) -> 17 | H22: =C22 -> 0.47931867 | I22: =D22 -> 0.86 | J22: =E22 -> 0.86 | K22: =ROUND(Notes!$B$4*I22+Notes!$B$5*H22+Notes!$B$6*J22,4) -> 0.7033 | L22: =RANK(K22,K$5:K$42,0) -> 17
A23: Portugal | B23: PRT | C23: =0.547953910556565 -> 0.54795391 | D23: =0.888411247396436 -> 0.88841125 | E23: =0.547953910556565 -> 0.54795391 | F23: =ROUND(Notes!$B$4*D23+Notes!$B$5*C23+Notes!$B$6*E23,4) -> 0.6975 | G23: =RANK(F23,F$5:F$42,0) -> 18 | H23: =C23 -> 0.54795391 | I23: =D23 -> 0.88841125 | J23: =E23 -> 0.54795391 | K23: =ROUND(Notes!$B$4*I23+Notes!$B$5*H23+Notes!$B$6*J23,4) -> 0.6975 | L23: =RANK(K23,K$5:K$42,0) -> 18
A24: Finland | B24: FIN | C24: =0.518965517241379 -> 0.51896552 | D24: =0.826923076923077 -> 0.82692308 | E24: =0.737888702767901 -> 0.7378887 | F24: =ROUND(Notes!$B$4*D24+Notes!$B$5*C24+Notes!$B$6*E24,4) -> 0.6869 | G24: =RANK(F24,F$5:F$42,0) -> 19 | H24: =C24 -> 0.51896552 | I24: =D24 -> 0.82692308 | J24: =E24 -> 0.7378887 | K24: =ROUND(Notes!$B$4*I24+Notes!$B$5*H24+Notes!$B$6*J24,4) -> 0.6869 | L24: =RANK(K24,K$5:K$42,0) -> 19
A25: Germany | B25: DEU | C25: =0.391406012913837 -> 0.39140601 | D25: =0.737888702767901 -> 0.7378887 | E25: =0.869865253929667 -> 0.86986525 | F25: =ROUND(Notes!$B$4*D25+Notes!$B$5*C25+Notes!$B$6*E25,4) -> 0.6149 | G25: =RANK(F25,F$5:F$42,0) -> 29 | H25: =C25 -> 0.39140601 | I25: =D25 -> 0.7378887 | J25: =E25 -> 0.86986525 | K25: =ROUND(Notes!$B$4*I25+Notes!$B$5*H25+Notes!$B$6*J25,4) -> 0.6149 | L25: =RANK(K25,K$5:K$42,0) -> 29
A26: Austria | B26: AUT | C26: =0.408845614108812 -> 0.40884561 | D26: =0.884365027341364 -> 0.88436503 | E26: =0.737888702767901 -> 0.7378887 | F26: =ROUND(Notes!$B$4*D26+Notes!$B$5*C26+Notes!$B$6*E26,4) -> 0.6668 | G26: =RANK(F26,F$5:F$42,0) -> 21 | H26: =C26 -> 0.40884561 | I26: =D26 -> 0.88436503 | J26: =E26 -> 0.7378887 | K26: =ROUND(Notes!$B$4*I26+Notes!$B$5*H26+Notes!$B$6*J26,4) -> 0.6668 | L26: =RANK(K26,K$5:K$42,0) -> 21
A27: Turkey | B27: TUR | C27: =0.431068736527055 -> 0.43106874 | D27: =0.864149148541634 -> 0.86414915 | E27: =0.69441435606903 -> 0.69441436 | F27: =ROUND(Notes!$B$4*D27+Notes!$B$5*C27+Notes!$B$6*E27,4) -> 0.6605 | G27: =RANK(F27,F$5:F$42,0) -> 22 | H27: =C27 -> 0.43106874 | I27: =D27 -> 0.86414915 | J27: =E27 -> 0.69441436 | K27: =ROUND(Notes!$B$4*I27+Notes!$B$5*H27+Notes!$B$6*J27,4) -> 0.6605 | L27: =RANK(K27,K$5:K$42,0) -> 22
A28: Slovenia | B28: SVN | C28: =0.391406012913837 -> 0.39140601 | D28: =0.869865253929667 -> 0.86986525 | E28: =0.737888702767901 -> 0.7378887 | F28: =ROUND(Notes!$B$4*D28+Notes!$B$5*C28+Notes!$B$6*E28,4) -> 0.6532 | G28: =RANK(F28,F$5:F$42,0) -> 23 | H28: =C28 -> 0.39140601 | I28: =D28 -> 0.86986525 | J28: =E28 -> 0.7378887 | K28: =ROUND(Notes!$B$4*I28+Notes!$B$5*H28+Notes!$B$6*J28,4) -> 0.6532 | L28: =RANK(K28,K$5:K$42,0) -> 23
A29: Australia | B29: AUS | C29: =0.479318672008477 -> 0.47931867 | D29: =0.851484971473245 -> 0.85148497 | E29: =0.547953910556565 -> 0.54795391 | F29: =ROUND(Notes!$B$4*D29+Notes!$B$5*C29+Notes!$B$6*E29,4) -> 0.653 | G29: =RANK(F29,F$5:F$42,0) -> 24 | H29: =C29 -> 0.47931867 | I29: =D29 -> 0.85148497 | J29: =E29 -> 0.54795391 | K29: =ROUND(Notes!$B$4*I29+Notes!$B$5*H29+Notes!$B$6*J29,4) -> 0.653 | L29: =RANK(K29,K$5:K$42,0) -> 24
A30: Denmark | B30: DNK | C30: =0.391406012913837 -> 0.39140601 | D30: =0.826923076923077 -> 0.82692308 | E30: =0.81340644290143 -> 0.81340644 | F30: =ROUND(Notes!$B$4*D30+Notes!$B$5*C30+Notes!$B$6*E30,4) -> 0.6456 | G30: =RANK(F30,F$5:F$42,0) -> 25 | H30: =C30 -> 0.39140601 | I30: =D30 -> 0.82692308 | J30: =E30 -> 0.81340644 | K30: =ROUND(Notes!$B$4*I30+Notes!$B$5*H30+Notes!$B$6*J30,4) -> 0.6456 | L30: =RANK(K30,K$5:K$42,0) -> 25
A31: Ireland | B31: IRL | C31: =0.479318672008477 -> 0.47931867 | D31: =0.787075165170195 -> 0.78707517 | E31: =0.646263719038607 -> 0.64626372 | F31: =ROUND(Notes!$B$4*D31+Notes!$B$5*C31+Notes!$B$6*E31,4) -> 0.6394 | G31: =RANK(F31,F$5:F$42,0) -> 26 | H31: =C31 -> 0.47931867 | I31: =D31 -> 0.78707517 | J31: =E31 -> 0.64626372 | K31: =ROUND(Notes!$B$4*I31+Notes!$B$5*H31+Notes!$B$6*J31,4) -> 0.6394 | L31: =RANK(K31,K$5:K$42,0) -> 26
A32: Greece | B32: GRC | C32: =0.479318672008477 -> 0.47931867 | D32: =0.737888702767901 -> 0.7378887 | E32: =0.737888702767901 -> 0.7378887 | F32: =ROUND(Notes!$B$4*D32+Notes!$B$5*C32+Notes!$B$6*E32,4) -> 0.6314 | G32: =RANK(F32,F$5:F$42,0) -> 27 | H32: =C32 -> 0.47931867 | I32: =D32 -> 0.7378887 | J32: =E32 -> 0.7378887 | K32: =ROUND(Notes!$B$4*I32+Notes!$B$5*H32+Notes!$B$6*J32,4) -> 0.6314 | L32: =RANK(K32,K$5:K$42,0) -> 27
A33: Netherlands | B33: NLD | C33: =0.338474732816403 -> 0.33847473 | D33: =0.813463195231154 -> 0.8134632 | E33: =0.869865253929667 -> 0.86986525 | F33: =ROUND(Notes!$B$4*D33+Notes!$B$5*C33+Notes!$B$6*E33,4) -> 0.6263 | G33: =RANK(F33,F$5:F$42,0) -> 28 | H33: =C33 -> 0.33847473 | I33: =D33 -> 0.8134632 | J33: =E33 -> 0.86986525 | K33: =ROUND(Notes!$B$4*I33+Notes!$B$5*H33+Notes!$B$6*J33,4) -> 0.6263 | L33: =RANK(K33,K$5:K$42,0) -> 28
A34: Spain | B34: ESP | C34: =0.391406012913837 -> 0.39140601 | D34: =0.778563038959402 -> 0.77856304 | E34: =0.737888702767901 -> 0.7378887 | F34: =ROUND(Notes!$B$4*D34+Notes!$B$5*C34+Notes!$B$6*E34,4) -> 0.6131 | G34: =RANK(F34,F$5:F$42,0) -> 30 | H34: =C34 -> 0.39140601 | I34: =D34 -> 0.77856304 | J34: =E34 -> 0.7378887 | K34: =ROUND(Notes!$B$4*I34+Notes!$B$5*H34+Notes!$B$6*J34,4) -> 0.6131 | L34: =RANK(K34,K$5:K$42,0) -> 30
A35: Japan | B35: JPN | C35: =0.278958448750364 -> 0.27895845 | D35: =0.859028659709284 -> 0.85902866 | E35: =0.787075165170195 -> 0.78707517 | F35: =ROUND(Notes!$B$4*D35+Notes!$B$5*C35+Notes!$B$6*E35,4) -> 0.6095 | G35: =RANK(F35,F$5:F$42,0) -> 31 | H35: =C35 -> 0.27895845 | I35: =D35 -> 0.85902866 | J35: =E35 -> 0.78707517 | K35: =ROUND(Notes!$B$4*I35+Notes!$B$5*H35+Notes!$B$6*J35,4) -> 0.6095 | L35: =RANK(K35,K$5:K$42,0) -> 31
A36: Norway | B36: NOR | C36: =0.373913043478261 -> 0.37391304 | D36: =0.781818181818182 -> 0.78181818 | E36: =0.737888702767901 -> 0.7378887 | F36: =ROUND(Notes!$B$4*D36+Notes!$B$5*C36+Notes!$B$6*E36,4) -> 0.6073 | G36: =RANK(F36,F$5:F$42,0) -> 32 | H36: =C36 -> 0.37391304 | I36: =D36 -> 0.78181818 | J36: =E36 -> 0.7378887 | K36: =ROUND(Notes!$B$4*I36+Notes!$B$5*H36+Notes!$B$6*J36,4) -> 0.6073 | L36: =RANK(K36,K$5:K$42,0) -> 32
A37: Poland | B37: POL | C37: =0.338474732816403 -> 0.33847473 | D37: =0.737888702767901 -> 0.7378887 | E37: =0.869865253929667 -> 0.86986525 | F37: =ROUND(Notes!$B$4*D37+Notes!$B$5*C37+Notes!$B$6*E37,4) -> 0.5932 | G37: =RANK(F37,F$5:F$42,0) -> 33 | H37: =C37 -> 0.33847473 | I37: =D37 -> 0.7378887 | J37: =E37 -> 0.86986525 | K37: =ROUND(Notes!$B$4*I37+Notes!$B$5*H37+Notes!$B$6*J37,4) -> 0.5932 | L37: =RANK(K37,K$5:K$42,0) -> 33
A38: Costa Rica | B38: CRI | C38: =0.278958448750364 -> 0.27895845 | D38: =0.822456690745778 -> 0.82245669 | E38: =0.737888702767901 -> 0.7378887 | F38: =ROUND(Notes!$B$4*D38+Notes!$B$5*C38+Notes!$B$6*E38,4) -> 0.5861 | G38: =RANK(F38,F$5:F$42,0) -> 34 | H38: =C38 -> 0.27895845 | I38: =D38 -> 0.82245669 | J38: =E38 -> 0.7378887 | K38: =ROUND(Notes!$B$4*I38+Notes!$B$5*H38+Notes!$B$6*J38,4) -> 0.5861 | L38: =RANK(K38,K$5:K$42,0) -> 34
A39: Hungary | B39: HUN | C39: =0.278958448750364 -> 0.27895845 | D39: =0.816200383417959 -> 0.81620038 | E39: =0.737888702767901 -> 0.7378887 | F39: =ROUND(Notes!$B$4*D39+Notes!$B$5*C39+Notes!$B$6*E39,4) -> 0.5834 | G39: =RANK(F39,F$5:F$42,0) -> 35 | H39: =C39 -> 0.27895845 | I39: =D39 -> 0.81620038 | J39: =E39 -> 0.7378887 | K39: =ROUND(Notes!$B$4*I39+Notes!$B$5*H39+Notes!$B$6*J39,4) -> 0.5834 | L39: =RANK(K39,K$5:K$42,0) -> 35
A40: Colombia | B40: COL | C40: =0.305956530933891 -> 0.30595653 | D40: =0.737888702767901 -> 0.7378887 | E40: =0.869865253929667 -> 0.86986525 | F40: =ROUND(Notes!$B$4*D40+Notes!$B$5*C40+Notes!$B$6*E40,4) -> 0.5798 | G40: =RANK(F40,F$5:F$42,0) -> 36 | H40: =C40 -> 0.30595653 | I40: =D40 -> 0.7378887 | J40: =E40 -> 0.86986525 | K40: =ROUND(Notes!$B$4*I40+Notes!$B$5*H40+Notes!$B$6*J40,4) -> 0.5798 | L40: =RANK(K40,K$5:K$42,0) -> 36
A41: New Zealand | B41: NZL | C41: =0.2 -> 0.2 | D41: =0.74468085106383 -> 0.74468085 | E41: =0.547953910556565 -> 0.54795391 | F41: =ROUND(Notes!$B$4*D41+Notes!$B$5*C41+Notes!$B$6*E41,4) -> 0.4911 | G41: =RANK(F41,F$5:F$42,0) -> 37 | H41: =C41 -> 0.2 | I41: =D41 -> 0.74468085 | J41: =E41 -> 0.54795391 | K41: =ROUND(Notes!$B$4*I41+Notes!$B$5*H41+Notes!$B$6*J41,4) -> 0.4911 | L41: =RANK(K41,K$5:K$42,0) -> 37
A42: Chile | B42: CHL | C42: =0.42321653857669 -> 0.42321654 | D42: =0.705977756078566 -> 0.70597776 | E42: =0 -> 0 | F42: =ROUND(Notes!$B$4*D42+Notes!$B$5*C42+Notes!$B$6*E42,4) -> 0.4842 | G42: =RANK(F42,F$5:F$42,0) -> 38 | H42: =C42 -> 0.42321654 | I42: =D42 -> 0.70597776 | J42: =E42 -> 0 | K42: =ROUND(Notes!$B$4*I42+Notes!$B$5*H42+Notes!$B$6*J42,4) -> 0.4842 | L42: =RANK(K42,K$5:K$42,0) -> 38

Sheet Consolidated
A1: Consolidated OECD rankings 2026-2030: current law vs. Canada immediate-expensing reform
A2: All values link to the per-year sheets. wavg = weighted average NPV; CL = current law.
A4: Country | B4: 2026 wavg CL | C4: 2026 rank CL | D4: 2026 wavg reform | E4: 2026 rank reform | F4: 2027 wavg CL | G4: 2027 rank CL | H4: 2027 wavg reform | I4: 2027 rank reform | J4: 2028 wavg CL | K4: 2028 rank CL | L4: 2028 wavg reform | M4: 2028 rank reform | N4: 2029 wavg CL | O4: 2029 rank CL | P4: 2029 wavg reform | Q4: 2029 rank reform | R4: 2030 wavg CL | S4: 2030 rank CL | T4: 2030 wavg reform | U4: 2030 rank reform
A5: ='2026'!A5 -> Estonia | B5: ='2026'!F5 -> 1 | C5: ='2026'!G5 -> 1 | D5: ='2026'!K5 -> 1 | E5: ='2026'!L5 -> 1 | F5: ='2027'!F5 -> 1 | G5: ='2027'!G5 -> 1 | H5: ='2027'!K5 -> 1 | I5: ='2027'!L5 -> 1 | J5: ='2028'!F5 -> 1 | K5: ='2028'!G5 -> 1 | L5: ='2028'!K5 -> 1 | M5: ='2028'!L5 -> 1 | N5: ='2029'!F5 -> 1 | O5: ='2029'!G5 -> 1 | P5: ='2029'!K5 -> 1 | Q5: ='2029'!L5 -> 1 | R5: ='2030'!F5 -> 1 | S5: ='2030'!G5 -> 1 | T5: ='2030'!K5 -> 1 | U5: ='2030'!L5 -> 1
A6: ='2026'!A6 -> Latvia | B6: ='2026'!F6 -> 1 | C6: ='2026'!G6 -> 1 | D6: ='2026'!K6 -> 1 | E6: ='2026'!L6 -> 1 | F6: ='2027'!F6 -> 1 | G6: ='2027'!G6 -> 1 | H6: ='2027'!K6 -> 1 | I6: ='2027'!L6 -> 1 | J6: ='2028'!F6 -> 1 | K6: ='2028'!G6 -> 1 | L6: ='2028'!K6 -> 1 | M6: ='2028'!L6 -> 1 | N6: ='2029'!F6 -> 1 | O6: ='2029'!G6 -> 1 | P6: ='2029'!K6 -> 1 | Q6: ='2029'!L6 -> 1 | R6: ='2030'!F6 -> 1 | S6: ='2030'!G6 -> 1 | T6: ='2030'!K6 -> 1 | U6: ='2030'!L6 -> 1
A7: ='2026'!A7 -> United States | B7: ='2026'!F7 -> 0.9452 | C7: ='2026'!G7 -> 3 | D7: ='2026'!K7 -> 0.9452 | E7: ='2026'!L7 -> 4 | F7: ='2027'!F7 -> 0.9452 | G7: ='2027'!G7 -> 3 | H7: ='2027'!K7 -> 0.9452 | I7: ='2027'!L7 -> 3 | J7: ='2028'!F7 -> 0.9452 | K7: ='2028'!G7 -> 3 | L7: ='2028'!K7 -> 0.9452 | M7: ='2028'!L7 -> 3 | N7: ='2029'!F7 -> 0.6774 | O7: ='2029'!G7 -> 20 | P7: ='2029'!K7 -> 0.6774 | Q7: ='2029'!L7 -> 20 | R7: ='2030'!F7 -> 0.6774 | S7: ='2030'!G7 -> 20 | T7: ='2030'!K7 -> 0.6774 | U7: ='2030'!L7 -> 20
A8: ='2026'!A8 -> Lithuania | B8: ='2026'!F8 -> 0.9288 | C8: ='2026'!G8 -> 4 | D8: ='2026'!K8 -> 0.9288 | E8: ='2026'!L8 -> 5 | F8: ='2027'!F8 -> 0.9288 | G8: ='2027'!G8 -> 4 | H8: ='2027'!K8 -> 0.9288 | I8: ='2027'!L8 -> 4 | J8: ='2028'!F8 -> 0.9288 | K8: ='2028'!G8 -> 4 | L8: ='2028'!K8 -> 0.9288 | M8: ='2028'!L8 -> 4 | N8: ='2029'!F8 -> 0.9288 | O8: ='2029'!G8 -> 3 | P8: ='2029'!K8 -> 0.9288 | Q8: ='2029'!L8 -> 3 | R8: ='2030'!F8 -> 0.9288 | S8: ='2030'!G8 -> 3 | T8: ='2030'!K8 -> 0.9288 | U8: ='2030'!L8 -> 3
A9: ='2026'!A9 -> Canada | B9: ='2026'!F9 -> 0.85 | C9: ='2026'!G9 -> 5 | D9: ='2026'!K9 -> 1 | E9: ='2026'!L9 -> 1 | F9: ='2027'!F9 -> 0.765 | G9: ='2027'!G9 -> 5 | H9: ='2027'!K9 -> 0.9149 | I9: ='2027'!L9 -> 5 | J9: ='2028'!F9 -> 0.765 | K9: ='2028'!G9 -> 5 | L9: ='2028'!K9 -> 0.9149 | M9: ='2028'!L9 -> 5 | N9: ='2029'!F9 -> 0.765 | O9: ='2029'!G9 -> 4 | P9: ='2029'!K9 -> 0.9149 | Q9: ='2029'!L9 -> 4 | R9: ='2030'!F9 -> 0.7462 | S9: ='2030'!G9 -> 7 | T9: ='2030'!K9 -> 0.9149 | U9: ='2030'!L9 -> 4
A10: ='2026'!A10 -> Italy | B10: ='2026'!F10 -> 0.7634 | C10: ='2026'!G10 -> 6 | D10: ='2026'!K10 -> 0.7634 | E10: ='2026'!L10 -> 6 | F10: ='2027'!F10 -> 0.7634 | G10: ='2027'!G10 -> 6 | H10: ='2027'!K10 -> 0.7634 | I10: ='2027'!L10 -> 6 | J10: ='2028'!F10 -> 0.7634 | K10: ='2028'!G10 -> 6 | L10: ='2028'!K10 -> 0.7634 | M10: ='2028'!L10 -> 6 | N10: ='2029'!F10 -> 0.7634 | O10: ='2029'!G10 -> 5 | P10: ='2029'!K10 -> 0.7634 | Q10: ='2029'!L10 -> 5 | R10: ='2030'!F10 -> 0.7634 | S10: ='2030'!G10 -> 4 | T10: ='2030'!K10 -> 0.7634 | U10: ='2030'!L10 -> 5
A11: ='2026'!A11 -> Korea | B11: ='2026'!F11 -> 0.7517 | C11: ='2026'!G11 -> 7 | D11: ='2026'!K11 -> 0.7517 | E11: ='2026'!L11 -> 7 | F11: ='2027'!F11 -> 0.7517 | G11: ='2027'!G11 -> 7 | H11: ='2027'!K11 -> 0.7517 | I11: ='2027'!L11 -> 7 | J11: ='2028'!F11 -> 0.7517 | K11: ='2028'!G11 -> 7 | L11: ='2028'!K11 -> 0.7517 | M11: ='2028'!L11 -> 7 | N11: ='2029'!F11 -> 0.7517 | O11: ='2029'!G11 -> 6 | P11: ='2029'!K11 -> 0.7517 | Q11: ='2029'!L11 -> 6 | R11: ='2030'!F11 -> 0.7517 | S11: ='2030'!G11 -> 5 | T11: ='2030'!K11 -> 0.7517 | U11: ='2030'!L11 -> 6
A12: ='2026'!A12 -> Iceland | B12: ='2026'!F12 -> 0.7468 | C12: ='2026'!G12 -> 8 | D12: ='2026'!K12 -> 0.7468 | E12: ='2026'!L12 -> 8 | F12: ='2027'!F12 -> 0.7468 | G12: ='2027'!G12 -> 8 | H12: ='2027'!K12 -> 0.7468 | I12: ='2027'!L12 -> 8 | J12: ='2028'!F12 -> 0.7468 | K12: ='2028'!G12 -> 8 | L12: ='2028'!K12 -> 0.7468 | M12: ='2028'!L12 -> 8 | N12: ='2029'!F12 -> 0.7468 | O12: ='2029'!G12 -> 7 | P12: ='2029'!K12 -> 0.7468 | Q12: ='2029'!L12 -> 7 | R12: ='2030'!F12 -> 0.7468 | S12: ='2030'!G12 -> 6 | T12: ='2030'!K12 -> 0.7468 | U12: ='2030'!L12 -> 7
A13: ='2026'!A13 -> France | B13: ='2026'!F13 -> 0.7419 | C13: ='2026'!G13 -> 9 | D13: ='2026'!K13 -> 0.7419 | E13: ='2026'!L13 -> 9 | F13: ='2027'!F13 -> 0.7419 | G13: ='2027'!G13 -> 9 | H13: ='2027'!K13 -> 0.7419 | I13: ='2027'!L13 -> 9 | J13: ='2028'!F13 -> 0.7419 | K13: ='2028'!G13 -> 9 | L13: ='2028'!K13 -> 0.7419 | M13: ='2028'!L13 -> 9 | N13: ='2029'!F13 -> 0.7419 | O13: ='2029'!G13 -> 8 | P13: ='2029'!K13 -> 0.7419 | Q13: ='2029'!L13 -> 8 | R13: ='2030'!F13 -> 0.7419 | S13: ='2030'!G13 -> 8 | T13: ='2030'!K13 -> 0.7419 | U13: ='2030'!L13 -> 8
A14: ='2026'!A14 -> Switzerland | B14: ='2026'!F14 -> 0.7411 | C14: ='2026'!G14 -> 10 | D14: ='2026'!K14 -> 0.7411 | E14: ='2026'!L14 -> 10 | F14: ='2027'!F14 -> 0.7411 | G14: ='2027'!G14 -> 10 | H14: ='2027'!K14 -> 0.7411 | I14: ='2027'!L14 -> 10 | J14: ='2028'!F14 -> 0.7411 | K14: ='2028'!G14 -> 10 | L14: ='2028'!K14 -> 0.7411 | M14: ='2028'!L14 -> 10 | N14: ='2029'!F14 -> 0.7411 | O14: ='2029'!G14 -> 9 | P14: ='2029'!K14 -> 0.7411 | Q14: ='2029'!L14 -> 9 | R14: ='2030'!F14 -> 0.7411 | S14: ='2030'!G14 -> 9 | T14: ='2030'!K14 -> 0.7411 | U14: ='2030'!L14 -> 9
A15: ='2026'!A15 -> Slovakia | B15: ='2026'!F15 -> 0.7391 | C15: ='2026'!G15 -> 11 | D15: ='2026'!K15 -> 0.7391 | E15: ='2026'!L15 -> 11 | F15: ='2027'!F15 -> 0.7391 | G15: ='2027'!G15 -> 11 | H15: ='2027'!K15 -> 0.7391 | I15: ='2027'!L15 -> 11 | J15: ='2028'!F15 -> 0.7391 | K15: ='2028'!G15 -> 11 | L15: ='2028'!K15 -> 0.7391 | M15: ='2028'!L15 -> 11 | N15: ='2029'!F15 -> 0.7391 | O15: ='2029'!G15 -> 10 | P15: ='2029'!K15 -> 0.7391 | Q15: ='2029'!L15 -> 10 | R15: ='2030'!F15 -> 0.7391 | S15: ='2030'!G15 -> 10 | T15: ='2030'!K15 -> 0.7391 | U15: ='2030'!L15 -> 10
A16: ='2026'!A16 -> Belgium | B16: ='2026'!F16 -> 0.7373 | C16: ='2026'!G16 -> 12 | D16: ='2026'!K16 -> 0.7373 | E16: ='2026'!L16 -> 12 | F16: ='2027'!F16 -> 0.7373 | G16: ='2027'!G16 -> 12 | H16: ='2027'!K16 -> 0.7373 | I16: ='2027'!L16 -> 12 | J16: ='2028'!F16 -> 0.7373 | K16: ='2028'!G16 -> 12 | L16: ='2028'!K16 -> 0.7373 | M16: ='2028'!L16 -> 12 | N16: ='2029'!F16 -> 0.7373 | O16: ='2029'!G16 -> 11 | P16: ='2029'!K16 -> 0.7373 | Q16: ='2029'!L16 -> 11 | R16: ='2030'!F16 -> 0.7373 | S16: ='2030'!G16 -> 11 | T16: ='2030'!K16 -> 0.7373 | U16: ='2030'!L16 -> 11
... A42: ='2026'!A42 -> Chile | B42: ='2026'!F42 -> 0.4842 | C42: ='2026'!G42 -> 38 | D42: ='2026'!K42 -> 0.4842 | E42: ='2026'!L42 -> 38 | F42: ='2027'!F42 -> 0.4842 | G42: ='2027'!G42 -> 38 | H42: ='2027'!K42 -> 0.4842 | I42: ='2027'!L42 -> 38 | J42: ='2028'!F42 -> 0.4842 | K42: ='2028'!G42 -> 38 | L42: ='2028'!K42 -> 0.4842 | M42: ='2028'!L42 -> 38 | N42: ='2029'!F42 -> 0.4842 | O42: ='2029'!G42 -> 38 | P42: ='2029'!K42 -> 0.4842 | Q42: ='2029'!L42 -> 38 | R42: ='2030'!F42 -> 0.4842 | S42: ='2030'!G42 -> 38 | T42: ='2030'!K42 -> 0.4842 | U42: ='2030'!L42 -> 38

Sheet Notes
A1: Notes and sources
A3: Asset weights (capital-stock shares; Devereux 2012), matching capital_cost_recovery.R
A4: w_machines | B4: =0.4391081 -> 0.4391081
A5: w_buildings | B5: =0.4116638 -> 0.4116638
A6: w_intangibles | B6: =0.1492281 -> 0.1492281
A8: Reform: Canada grants immediate expensing (NPV = 1.0) for machinery and buildings from 2026 onward; intangibles remain on current law.
A9: Weighted average = w_machines*machinery + w_buildings*buildings + w_intangibles*intangibles.
A10: Ranking: RANK on the weighted average rounded to 4 dp, within the 38 OECD countries, descending, ties assigned the minimum rank (matches R rank(-round(x,4), ties.method="min")).
A11: OECD ranking excludes the 5 EU-but-not-OECD countries in the dataset: Bulgaria, Croatia, Cyprus, Malta, Romania.
A12: Source data: final-data/npv_all_years.csv (produced by capital_cost_recovery.R). Canada per-asset scenario: final-outputs/canada_expensing_scenario.csv.
A13: Current-law forecasts for all 38 countries extend through 2030; the ranking window is 2026-2030 for that reason.
